{
    "Elettra": "Lambo"
}[
    {
        "delivered-to": [
            "ifchasethenhire@gmail.com"
        ],
        "received": [
            "by 2002:a05:6214:36c:0:0:0:0 with SMTP id t12csp274408qvu; Mon, 3 Feb 2020 17:32:51 -0800 (PST)",
            "from mail-sor-f41.google.com (mail-sor-f41.google.com. [209.85.220.41]) by mx.google.com with SMTPS id i9sor4200569iop.77.2020.02.03.17.32.51 for <ifchasethenhire@gmail.com> (Google Transport Security); Mon, 03 Feb 2020 17:32:51 -0800 (PST)"
        ],
        "x-received": [
            "by 2002:a92:3c93:: with SMTP id j19mr16767119ilf.63.1580779971850; Mon, 03 Feb 2020 17:32:51 -0800 (PST)",
            "by 2002:a6b:8ec9:: with SMTP id q192mr21906605iod.237.1580779971455; Mon, 03 Feb 2020 17:32:51 -0800 (PST)"
        ],
        "arc-seal": [
            "i=1; a=rsa-sha256; t=1580779971; cv=none; d=google.com; s=arc-20160816; b=fexucKcKFi7sbmf2gBriY7A4hjE5fpfjXnZ3AZUhG+s8hGwyc5NFlT4+2RFdTpb7FA Tfm8D0XnsosuUcUItNSCppEVVrlF/2xH/gS5z/VXl5E3PgvHj1mYj8yTNsEtQt6ynS7h DLzFbT37cx29GTtQBrqHuSLVay9O9b063HuhMYs7IROdRqnrG4vFi3lZxLidT+oAa+zq HXsmn8fwpFR5U8oowOmW37xbFrNmrk4NDANgpZU+hZkp0m2o1q6mbhQiMvd4B0Kl5GOe h8sbBJfABgQHWmwbRn0UfBV6HtEj9RXp2GLZRGWiHajL+X5eamV3h62FLoIkc8Wv1KCs CFUA=="
        ],
        "arc-message-signature": [
            "i=1; a=rsa-sha256; c=relaxed/relaxed; d=google.com; s=arc-20160816; h=to:subject:message-id:date:from:in-reply-to:references:mime-version :dkim-signature; bh=jez3DyTsNFf70qRKjy2Yud/6vtsPaStNk/QgkyGY/9o=; b=bGCsZb+Z4uBo8coEz5Isdih8NuQt06ehjF8jBFZtrj+htCaiPRVsNw+y17zqI6XfkN AVJUIBhn/29Yh+ueHM3FIpT/kihugNKYKxIce+9gQyvgEjqLkmFCJBe65u0ohGR4wiuB +ZF04hNjioO0tvzlVnYnHqC0cndXcg/Ls86OR8JRSGB0cBoJRA2xsVEnNIvQpnwL55FT RhIiQTzEc06q9ZdiII8O0h+XAdXgenA2YMfNgyt9I2/neItHC/9fINlEeBAlPgTgdCYQ V9yHAMeypFpFpQ3vh4o2+g2H1sLMhZ8jbrd2OvaQR24c1DAo+XhZEjPVPC0OBDloZls5 5M/w=="
        ],
        "arc-authentication-results": [
            "i=1; mx.google.com; dkim=pass header.i=@gmail.com header.s=20161025 header.b=CYlIEcVk; spf=pass (google.com: domain of 0tto.mastr@gmail.com designates 209.85.220.41 as permitted sender) smtp.mailfrom=0tto.mastr@gmail.com; dmarc=pass (p=NONE sp=QUARANTINE dis=NONE) header.from=gmail.com"
        ],
        "return-path": [
            "<0tto.mastr@gmail.com>"
        ],
        "received-spf": [
            "pass (google.com: domain of 0tto.mastr@gmail.com designates 209.85.220.41 as permitted sender) client-ip=209.85.220.41;"
        ],
        "authentication-results": [
            "mx.google.com; dkim=pass header.i=@gmail.com header.s=20161025 header.b=CYlIEcVk; spf=pass (google.com: domain of 0tto.mastr@gmail.com designates 209.85.220.41 as permitted sender) smtp.mailfrom=0tto.mastr@gmail.com; dmarc=pass (p=NONE sp=QUARANTINE dis=NONE) header.from=gmail.com"
        ],
        "dkim-signature": [
            "v=1; a=rsa-sha256; c=relaxed/relaxed; d=gmail.com; s=20161025; h=mime-version:references:in-reply-to:from:date:message-id:subject:to; bh=jez3DyTsNFf70qRKjy2Yud/6vtsPaStNk/QgkyGY/9o=; b=CYlIEcVkqgl7yQKcRgChEutANda32SlunxSA+FUjFX7dNwh99zuFerxT5dJfo+gMg8 BOyM2Eu1P9DCCX0AbBQ1BeeBUaGzTPR8tvyyeGmAeIArdWj2bi/LXV4AKc03ckI35lSe HzsLL+c0AUHBLMavufB2ixIwM/EaLDbt2yAmbZ3dko5lFJBJC/IRJ1zYGQfwA8DbhnO9 RLB0z6MvuX0JDBfnPxP86VcVyBZf/oFnyPmeb6owL+iDeqW8V8FKgE+SyRZSzAGJyyq5 5m97F5QyJwoAsCcEbjCgppHawpAHfKw6cE5je0DmuDUabNT1H79Q3yeyVRAptpg4KlpU ijkw=="
        ],
        "x-google-dkim-signature": [
            "v=1; a=rsa-sha256; c=relaxed/relaxed; d=1e100.net; s=20161025; h=x-gm-message-state:mime-version:references:in-reply-to:from:date :message-id:subject:to; bh=jez3DyTsNFf70qRKjy2Yud/6vtsPaStNk/QgkyGY/9o=; b=oREdhbsJ5W1Fi6LHqJiTxU5Pr+j8rm+66Ecfovvu/uzn3xtJWT+CpVAN/Zt6cgRAfN lrJcXo2Lp/dv9z6TcBRl6ISevckm1adCkB3r7aSTxxsZZR2UHGExwwOZAnoYNY5qt7ZR yt7MASA3+1h2oCN/8GuUTXpde7HxKWutOZW76lfScMPvW+fb2yvaiBM3/6thWuAfEkOT a5Y0fVWwr2Le7WcbqdIgLn4F1JL+lfXQi6wESOCBmvVkf2Qy2AiMhAAy1qCPfdjDHqTo dWrnv0Q+vS98pujy2fNkNSug1z6G3Z791qGKY5ws8iCZecSW0FynnE59i64FGtfFVo5W SMtw=="
        ],
        "x-gm-message-state": [
            "APjAAAUeKV/ZrmIC8epW5PQWecV6E6G/6cNcc32bz2AA+xi3qnuh8RJY NBFzr/GuLBKAAlysYG9eSGlKl38yU1E5gre+9cZ6dQ=="
        ],
        "x-google-smtp-source": [
            "APXvYqzGTuIodjQhfwYFSVKsBAoYGtE9vcoUauyc9eCgN3wheNDhUFarhTezhtMTcQki1EFv93rQs8PN+Hv7M6Hm2qw="
        ],
        "mime-version": [
            "1.0"
        ],
        "references": [
            "<731bc3e1-b1d0-fb08-807a-5068ee56d351@gmail.com>"
        ],
        "in-reply-to": [
            "<731bc3e1-b1d0-fb08-807a-5068ee56d351@gmail.com>"
        ],
        "from": [
            "Otto Heidebur <0tto.mastr@gmail.com>"
        ],
        "date": [
            "Mon, 3 Feb 2020 17:32:39 -0800"
        ],
        "message-id": [
            "<CAK5jdh+Bq0vCM1pNnp9KdpNa4htF_RzW+ja+Rtnhs+wmqpz8FQ@mail.gmail.com>"
        ],
        "subject": [
            "Re: Hey beautiful!"
        ],
        "to": [
            "ifchasethenhire@gmail.com"
        ],
        "content-type": [
            "multipart/alternative; boundary=\"000000000000aaaf63059db60473\""
        ]
    }
][
    {
        "delivered-to": [
            "ifchasethenhire@gmail.com"
        ],
        "received": [
            "by 2002:a05:6214:36c:0:0:0:0 with SMTP id t12csp279129qvu; Mon, 3 Feb 2020 17:38:51 -0800 (PST)",
            "from mail-sor-f41.google.com (mail-sor-f41.google.com. [209.85.220.41]) by mx.google.com with SMTPS id l17sor12861393ilm.63.2020.02.03.17.38.50 for <ifchasethenhire@gmail.com> (Google Transport Security); Mon, 03 Feb 2020 17:38:51 -0800 (PST)"
        ],
        "x-received": [
            "by 2002:a5e:8e4d:: with SMTP id r13mr19855860ioo.60.1580780331039; Mon, 03 Feb 2020 17:38:51 -0800 (PST)",
            "by 2002:a92:d189:: with SMTP id z9mr16963944ilz.191.1580780330532; Mon, 03 Feb 2020 17:38:50 -0800 (PST)"
        ],
        "arc-seal": [
            "i=1; a=rsa-sha256; t=1580780331; cv=none; d=google.com; s=arc-20160816; b=ZJzJfjrDaTXKnWMMcc3gEosYcfZV17kYTaW2QvnOalTxcjB+OL/iGpgnLEDIyoJt1W /EJUoRum1cDD7P5dl9fsRgUPe7oc21y7GmTiTio/kp989BJ30B1Vjgff13nRSJDqs9jQ vnQoExOitFc2OjMnQ3LDyofwI15tTJ5ouoVox6i/Iooo323DcQNSkpK8ek4ebfVSlkwo 71w0/4MjC44FYeoPK9cjT2SUkQQy7xHjqqK406q68e6OAw9cypvR81Vo5tc4zW4W1g1w h1nJL8ScOjT7fUiEE9B8ML2zmN+sNIBPNiuSiBweJzHEP83dr8r4UJSN3k67PpSftH7J byCA=="
        ],
        "arc-message-signature": [
            "i=1; a=rsa-sha256; c=relaxed/relaxed; d=google.com; s=arc-20160816; h=to:subject:message-id:date:from:mime-version:dkim-signature; bh=Ctx23ShvzYcnzQwfEeW31NNDaCgg4QBQTghN75Jddr0=; b=cSQYC7IePojEpPDHEotWkM/s6ePBKoTVbvXukwLCBH6dAKk0jZj+wCfgB0f2eRuayj YLEVm0U/ZtQjDmvn1m949M8XzPEr9t2qBfaoieXr3PAg3RA10xE4yH42sIDb4B/bIx5S YIh+6cLzGf7f+9EKsXOfgbgHU/HEpz86B/OWz7HQOQSIdTwAtDemPMN88T0XTdTbMxrM hsMwNds+KPhjhJPXJeNxHu/zMfYc8ofv2I5QRWsNM1dnJxHJLo0JlZd/8noP9NrgLDki va4BPE6x9jmbAcSPyeBmwNOc/kAUYxH/hudh0E8L1SUA2Q8kFn6ZjErv7sQQZpZYdMZU Iu6g=="
        ],
        "arc-authentication-results": [
            "i=1; mx.google.com; dkim=pass header.i=@gmail.com header.s=20161025 header.b=cpDNXajZ; spf=pass (google.com: domain of 0tto.mastr@gmail.com designates 209.85.220.41 as permitted sender) smtp.mailfrom=0tto.mastr@gmail.com; dmarc=pass (p=NONE sp=QUARANTINE dis=NONE) header.from=gmail.com"
        ],
        "return-path": [
            "<0tto.mastr@gmail.com>"
        ],
        "received-spf": [
            "pass (google.com: domain of 0tto.mastr@gmail.com designates 209.85.220.41 as permitted sender) client-ip=209.85.220.41;"
        ],
        "authentication-results": [
            "mx.google.com; dkim=pass header.i=@gmail.com header.s=20161025 header.b=cpDNXajZ; spf=pass (google.com: domain of 0tto.mastr@gmail.com designates 209.85.220.41 as permitted sender) smtp.mailfrom=0tto.mastr@gmail.com; dmarc=pass (p=NONE sp=QUARANTINE dis=NONE) header.from=gmail.com"
        ],
        "dkim-signature": [
            "v=1; a=rsa-sha256; c=relaxed/relaxed; d=gmail.com; s=20161025; h=mime-version:from:date:message-id:subject:to; bh=Ctx23ShvzYcnzQwfEeW31NNDaCgg4QBQTghN75Jddr0=; b=cpDNXajZWn9Xz09TKikflfETIyuCgHw0dZ4YN+zzBpD9sbtfWVKGSOhzmqcVfhCHl6 rubui6SZnJGBeZNVHKNtpTZtbwTCryh/Oo67l7OynknagK1cqO+hme5tMGqKf0ZV+FsQ 13YP8LOENhVku6+vywiY0L2KAgSipv++02ks1qo2olBbpjQToMgrGpIZsu56qBwchHRI 4Yln6w2wl7B+Cg3tlZ+Pr/Sf/qSLMYpcbfSpKvDHWNexxk0vPfQDbyxdh89PduWRtYnD IbZaMYN+WpVGxqTFbBcqu16S/8UNrcT3qtlrL9Zl+UXUG/0+UZksJY86xnaW9EVZv18q KH8A=="
        ],
        "x-google-dkim-signature": [
            "v=1; a=rsa-sha256; c=relaxed/relaxed; d=1e100.net; s=20161025; h=x-gm-message-state:mime-version:from:date:message-id:subject:to; bh=Ctx23ShvzYcnzQwfEeW31NNDaCgg4QBQTghN75Jddr0=; b=n3Q6cBkuPw0pFEmc8P1KmZ94k0xO+pcumjjPdO9LADt0UZ28xvHNerCl/jvq5VYG4f 1oJTX0ajMoa4yguRiIQzUwLuR99uk96YD27bzjsEMVHAJA1o3QsqT3hClgM6y6eIMAKf myU3aQfWX2FvDZpnowzKodn2o/GBDpwpCQXxsuhS3Y+zV4OVPRuLjUG70PNAWF5pirw4 EmNKi2aTCBbhqgvQ45wYOmZTp25ztcNkCQX5+asynjpVs+oKHucoTlAzQDZQHyrUFS+J rrGEKuuCedhVlMpZ9/o3T+1aeiuI2yX0n2Xt9hl3J5HA3iJeVFTiIPtu5oq119O7CdQt duOw=="
        ],
        "x-gm-message-state": [
            "APjAAAUwwWTvdh8TezkM3JUn2L4bAPgwlcuPVfvD0Q9dc0RtWzBenpuw /P+e6utE5vSQHNYusgfLth7c/boDLRzxAuQOE5A3rQ=="
        ],
        "x-google-smtp-source": [
            "APXvYqyPGzV8vMwiTdwasxH4Frhr0ZZinn4mdaQMO2/mOsBxWpQQ7JIUlpquyjZlW+tdEZFT+uynC3sXzFCTGMXMpgs="
        ],
        "mime-version": [
            "1.0"
        ],
        "from": [
            "Otto Heidebur <0tto.mastr@gmail.com>"
        ],
        "date": [
            "Mon, 3 Feb 2020 17:38:38 -0800"
        ],
        "message-id": [
            "<CAK5jdh+s4pTt46nw7aAL1UQ=vEMoBNPzeSjCx-AKBjJRWKObSA@mail.gmail.com>"
        ],
        "subject": [
            "Ddd"
        ],
        "to": [
            "ifchasethenhire@gmail.com"
        ],
        "content-type": [
            "multipart/alternative; boundary=\"00000000000011c29c059db61ab9\""
        ]
    }
][
    {
        "delivered-to": [
            "ifchasethenhire@gmail.com"
        ],
        "received": [
            "by 2002:a05:6214:36c:0:0:0:0 with SMTP id t12csp368591qvu; Mon, 3 Feb 2020 19:18:27 -0800 (PST)",
            "from mail-sor-f41.google.com (mail-sor-f41.google.com. [209.85.220.41]) by mx.google.com with SMTPS id p8sor30858594jah.13.2020.02.03.19.18.27 for <ifchasethenhire@gmail.com> (Google Transport Security); Mon, 03 Feb 2020 19:18:27 -0800 (PST)"
        ],
        "x-received": [
            "by 2002:a92:5c5c:: with SMTP id q89mr17686771ilb.66.1580786307302; Mon, 03 Feb 2020 19:18:27 -0800 (PST)",
            "by 2002:a02:9203:: with SMTP id x3mr21494003jag.62.1580786306677; Mon, 03 Feb 2020 19:18:26 -0800 (PST)"
        ],
        "arc-seal": [
            "i=1; a=rsa-sha256; t=1580786307; cv=none; d=google.com; s=arc-20160816; b=hHAADn9SHqRpaLbJf7rHI/467MHPyHqSKbdq0C9Sd5oOwztrM2vFccH0jr/6ZxXncS 92OxMhWdPTIW3SFR3pOyZV4/+wxz4cM9PL95lHoNcLYkuM3yPm2MkShbSE4gwmq56WLU a+FU/KwVCPccjCiN9ukkEg97UdcLmQolVCDE+gMpS6cP56eOseeeDxG1fJ4ZVFYN4EA6 yfKwfKLoe96iq50uI08OjVNzWoZAKZn4g9yPjO19Wlv8bEv+5dYo7Ma+tDgp8mvlieTY mrg57CtTkPEaoI6tMTXL7B0QzvGfGPYRLHhZaupXlDFjgchoybBWh9vZ3ULLhnUcEqcu p3BA=="
        ],
        "arc-message-signature": [
            "i=1; a=rsa-sha256; c=relaxed/relaxed; d=google.com; s=arc-20160816; h=to:subject:message-id:date:from:mime-version:dkim-signature; bh=P1+EKJu/j8NRXJv5s7M2cUhFZrwP8UmwOa+8jThGE/Q=; b=U/pUIIAZ6O4pn9LZySLRUhplxsdbTzs5iOruJnhCA2CMchtat0WqYALizJCKkkJqlu 20885U2A+xtrIH6EgsRJOeop3aFAJAUk1QyGW1ByrUztpqzZcKatXjbXCAW86eDeZhQV 7gqhXgBE8XFlhNVGvot4xouIDoS1C3IIqSnojOgQWf+zg9STxEqBpWtWcwpdJIC3pXZ4 W6vmURszn3/2/YNd+UVtFF1RA50Qw/I3v6MMEPWZb5cFxtu/VVRj5vbEyiFk8/iex1LR oJE3JVn4QNM6NrJVJfzaPyf4U8fRRM/karesn7gP48WmNrfMpXJ2bVnSYoZ2bUgsRHpj YcIw=="
        ],
        "arc-authentication-results": [
            "i=1; mx.google.com; dkim=pass header.i=@gmail.com header.s=20161025 header.b=TaBqLNtC; spf=pass (google.com: domain of 0tto.mastr@gmail.com designates 209.85.220.41 as permitted sender) smtp.mailfrom=0tto.mastr@gmail.com; dmarc=pass (p=NONE sp=QUARANTINE dis=NONE) header.from=gmail.com"
        ],
        "return-path": [
            "<0tto.mastr@gmail.com>"
        ],
        "received-spf": [
            "pass (google.com: domain of 0tto.mastr@gmail.com designates 209.85.220.41 as permitted sender) client-ip=209.85.220.41;"
        ],
        "authentication-results": [
            "mx.google.com; dkim=pass header.i=@gmail.com header.s=20161025 header.b=TaBqLNtC; spf=pass (google.com: domain of 0tto.mastr@gmail.com designates 209.85.220.41 as permitted sender) smtp.mailfrom=0tto.mastr@gmail.com; dmarc=pass (p=NONE sp=QUARANTINE dis=NONE) header.from=gmail.com"
        ],
        "dkim-signature": [
            "v=1; a=rsa-sha256; c=relaxed/relaxed; d=gmail.com; s=20161025; h=mime-version:from:date:message-id:subject:to; bh=P1+EKJu/j8NRXJv5s7M2cUhFZrwP8UmwOa+8jThGE/Q=; b=TaBqLNtCHHOMsfPVHZrrTyxKlBc3eaOMFAMGYvYM5ZAHrCkpXrEQYBZ4lUsKoiDv8+ em8aybC2jgEvxlXWFcMpn4j31bS1pwizVXOZMk9Z5+TZGKbwnxFx6EYGGVwgUVoWZyP5 ltDM7kW4RkiGZBwCbVY15e+i1VZsV0p/HaZqZoyQn9keyQO4PHQBWwX6+ea6rvwwUyBE UknWX1ftJufp2+R2AUD/wFKyUnhS7GrCZGVb/Lud5Sz8xv9KsfpiPkNkKwP/Clg8CfUU eWX3moYOYyQxNJHGSAjpkMnd7JhWdEQPZ6bCm1We1cINo5uOyWzLa+M0bXzE6JKfoIl0 gMKw=="
        ],
        "x-google-dkim-signature": [
            "v=1; a=rsa-sha256; c=relaxed/relaxed; d=1e100.net; s=20161025; h=x-gm-message-state:mime-version:from:date:message-id:subject:to; bh=P1+EKJu/j8NRXJv5s7M2cUhFZrwP8UmwOa+8jThGE/Q=; b=RbuUCC6dceQk7dIAw4MU5a+U12OYnhkha/QP5xU0w+BAdLV5qpfHwPhOhW6QiUBeYS /zGL8wGLQGFAY43Hs7rZmu/1ofJPzD8zEXwcXkX5AqXy+84YOrTjqhww6Z4QDnP0MHqn Wj+ze6mos+VHya+H4+GqNv46eGYfS5vCiUvdJOUMiF1Y5etD9WJBLpkQh7WdUv1JIU06 NLV3j79gwPagBktXd0pwFsWqDVEYBkQDO+QXDFBDxQtuXO2MOecGv+eqQN7+EJYI9cdZ LO7tZOayN2ZaJ+BRNTqA0fcdi3rpOztcRPTH5kgRF1o7nzNKlGmfDQ9RZ47eQo5j8SnL lBxw=="
        ],
        "x-gm-message-state": [
            "APjAAAWA+s8Rjow1YS9dumKLO4nIpmTIIf0rB+ld8sWYzvdJzBOMGWpw XaBPTwAbENecTh6BVarfUFfxYekTHQk0sSj1+de1cQ=="
        ],
        "x-google-smtp-source": [
            "APXvYqyxfcUFEGRNDwXQaNG2rIgu6MfE47CUBjjg8aezxzyVMri464JcohQQXYTlfa7rQncgWzhVABwe7+Fmop8vBEU="
        ],
        "mime-version": [
            "1.0"
        ],
        "from": [
            "Otto Heidebur <0tto.mastr@gmail.com>"
        ],
        "date": [
            "Mon, 3 Feb 2020 19:18:13 -0800"
        ],
        "message-id": [
            "<CAK5jdh+gPesegX8hidCLAeFt3A8NOWOSf9OYdPGrc7LU6yoxaQ@mail.gmail.com>"
        ],
        "subject": [
            "Tttgg"
        ],
        "to": [
            "ifchasethenhire@gmail.com"
        ],
        "content-type": [
            "multipart/alternative; boundary=\"000000000000468155059db77e4e\""
        ]
    }
][
    {
        "delivered-to": [
            "ifchasethenhire@gmail.com"
        ],
        "received": [
            "by 2002:a05:6214:36c:0:0:0:0 with SMTP id t12csp369999qvu; Mon, 3 Feb 2020 19:20:01 -0800 (PST)",
            "from mail-sor-f41.google.com (mail-sor-f41.google.com. [209.85.220.41]) by mx.google.com with SMTPS id f81sor12547201ilg.107.2020.02.03.19.20.01 for <ifchasethenhire@gmail.com> (Google Transport Security); Mon, 03 Feb 2020 19:20:01 -0800 (PST)"
        ],
        "x-received": [
            "by 2002:a5e:c707:: with SMTP id f7mr19420193iop.160.1580786401904; Mon, 03 Feb 2020 19:20:01 -0800 (PST)",
            "by 2002:a92:dac3:: with SMTP id o3mr18920719ilq.237.1580786401611; Mon, 03 Feb 2020 19:20:01 -0800 (PST)"
        ],
        "arc-seal": [
            "i=1; a=rsa-sha256; t=1580786401; cv=none; d=google.com; s=arc-20160816; b=I5lxIQtIehgYSXfq1kUjaLbiMpLkbZHa4/YYOko+8hwv9FdIuPnoHyteAMIvT7Wmke KHhfOSYEOU4Ykn2UJTDd9KS3Hb8yftCXzcwx1AI4JRVsmLM/AeWM/BnDE8Nt02CeNLCW 0z+7nLvQBTpMlJqtF8QvtujWA9fpBNeX8MjgdeyMeoXPlB01PoVhQux5OYNB+E+mhpMq LM2/Fnk96ncrrU/AZ6HXx4hQLJLurJXa1b4UaMcr+vrUxrOrNUhLl8bCe9n4OwmhGXgQ eGME6+U6Iu4rSMnPePySUC5AeJa7ZJI5EAJfm941yf94mqn2HBQrF3xO0SneYETltBX8 wIrQ=="
        ],
        "arc-message-signature": [
            "i=1; a=rsa-sha256; c=relaxed/relaxed; d=google.com; s=arc-20160816; h=to:subject:message-id:date:from:mime-version:dkim-signature; bh=LF4tLyqSThMoAc56qCsOssj4uULDKju/dgJtsPadOIQ=; b=XOoo3h+qvxA5vyePJSVtMnHcEIBYZmY8SpKYl/TeIdB6OgqyHD9c8WJcFuTjwyhw8o lU8aECB4NwZ/uCcEjTISLDM7TXbL/r4UoyTSkEulefNIHuG/rUAwlg67/KPzvK/Q08E+ DjhZh0OphVzAGrd2wfRQo9O1N9Cu6BvxQlX4ynrBq6/z23SxSUkIVSGOldB58C4FLHHQ 1/n61pq+gTraXgLkeNojBuNk3ItuiiSSpOhWygB+nPAO2nes31jC3UwjQzyNHFKFd3jq gr69lrs2I7u+jKJrHANX1bWYhz739gbPDhegthcLcFrp6KVlMJxXq3tTkg5fnK3Wqcx/ 9yTg=="
        ],
        "arc-authentication-results": [
            "i=1; mx.google.com; dkim=pass header.i=@gmail.com header.s=20161025 header.b=JUel6qCz; spf=pass (google.com: domain of 0tto.mastr@gmail.com designates 209.85.220.41 as permitted sender) smtp.mailfrom=0tto.mastr@gmail.com; dmarc=pass (p=NONE sp=QUARANTINE dis=NONE) header.from=gmail.com"
        ],
        "return-path": [
            "<0tto.mastr@gmail.com>"
        ],
        "received-spf": [
            "pass (google.com: domain of 0tto.mastr@gmail.com designates 209.85.220.41 as permitted sender) client-ip=209.85.220.41;"
        ],
        "authentication-results": [
            "mx.google.com; dkim=pass header.i=@gmail.com header.s=20161025 header.b=JUel6qCz; spf=pass (google.com: domain of 0tto.mastr@gmail.com designates 209.85.220.41 as permitted sender) smtp.mailfrom=0tto.mastr@gmail.com; dmarc=pass (p=NONE sp=QUARANTINE dis=NONE) header.from=gmail.com"
        ],
        "dkim-signature": [
            "v=1; a=rsa-sha256; c=relaxed/relaxed; d=gmail.com; s=20161025; h=mime-version:from:date:message-id:subject:to; bh=LF4tLyqSThMoAc56qCsOssj4uULDKju/dgJtsPadOIQ=; b=JUel6qCz5iLX+4ATSkI6q4LviTh6DtnfJPemYJPevWrzyb9KsMHgIFaTXwn/hrt0Os NfTnnRlpa2B4OQHLgXph9y4aMDkC/hMFlCL4R7EoqwjxHS8AH1almfXhMCALBWB3Pb4o WKzeIIZAxOYXWN0dZumP8PNi2DNwoTKKuKMe2NBVrMABOh+3jrXSzdZatRiKHyr6BXCL unVFa7SfYq9H/RvFkUGpdHCeW9pS014lL4t7+UX+Ucy/+kE8Y0Pwzy3qw/IDt4Cy1Nnf DRPDmHlZAj7xlRjFjXIUEGQqyNXxK0umv3ol12wifl5rpFD2cB12IVFC+zWphgmhaZ2c sEjw=="
        ],
        "x-google-dkim-signature": [
            "v=1; a=rsa-sha256; c=relaxed/relaxed; d=1e100.net; s=20161025; h=x-gm-message-state:mime-version:from:date:message-id:subject:to; bh=LF4tLyqSThMoAc56qCsOssj4uULDKju/dgJtsPadOIQ=; b=LUtdU2Gp3H3v6FPLRZMAkvaHw6KtrpyA3AycntVEdw29VK7mVKnK0Av/89whryQHt1 qMT2GWtBy3OjBcyszRil+Mdh4rF2s/BE0SycUiYvlH2k3S4iA3LDmXcrLh9QqV8KPzVU aEeCJBxP929FFgKv0uAi95rVi6lbG/L5VWG8cPUy/+RGR5VJfyNF/xYrkRkOyT5/CkYM Q54S1Y9QC4B+5WyQrYwa4RJ0g/3YUS+MArNINiG+YMttAQQSWoQk/+a+IN6SJO3Iixol 5rONoViPpKNGzwI9AVHOoOaFoMjdpYprZsSEDBg1BH1pe0/zEvBGJocu/RLMlDPkEow1 iLuw=="
        ],
        "x-gm-message-state": [
            "APjAAAVNdUgxFFw+NbspyRUUIh/q3TLoz8IlM69XCHBL0JbB5KL0AO44 9n+JFj14h/9zkhcMF0Xbyvmr0VFDxzyF7pu4ixZtEQ=="
        ],
        "x-google-smtp-source": [
            "APXvYqwqC43mo1TjKWuJyaiNKCo2VhgsCZnx7tEbtnVUb0m1MipP3A9Q0ko1/MWkGs/YYm7cORCEr+vitwxAIZui7LE="
        ],
        "mime-version": [
            "1.0"
        ],
        "from": [
            "Otto Heidebur <0tto.mastr@gmail.com>"
        ],
        "date": [
            "Mon, 3 Feb 2020 19:19:50 -0800"
        ],
        "message-id": [
            "<CAK5jdh+wQmFd3nQc4=U3TRWkYKxhmqYWgJ4ow3--C96v1F9+aQ@mail.gmail.com>"
        ],
        "subject": [
            "Nend"
        ],
        "to": [
            "ifchasethenhire@gmail.com"
        ],
        "content-type": [
            "multipart/alternative; boundary=\"000000000000ef126c059db783c1\""
        ]
    }
][
    {
        "delivered-to": [
            "ifchasethenhire@gmail.com"
        ],
        "received": [
            "by 2002:a05:6214:36c:0:0:0:0 with SMTP id t12csp379246qvu; Mon, 3 Feb 2020 19:31:09 -0800 (PST)",
            "from mail-sor-f41.google.com (mail-sor-f41.google.com. [209.85.220.41]) by mx.google.com with SMTPS id 22sor14166314iof.132.2020.02.03.19.31.09 for <ifchasethenhire@gmail.com> (Google Transport Security); Mon, 03 Feb 2020 19:31:09 -0800 (PST)"
        ],
        "x-received": [
            "by 2002:a5d:8146:: with SMTP id f6mr20981404ioo.93.1580787069792; Mon, 03 Feb 2020 19:31:09 -0800 (PST)",
            "by 2002:a6b:e601:: with SMTP id g1mr21549033ioh.55.1580787069306; Mon, 03 Feb 2020 19:31:09 -0800 (PST)"
        ],
        "arc-seal": [
            "i=1; a=rsa-sha256; t=1580787069; cv=none; d=google.com; s=arc-20160816; b=pjWR200fe/HQnpdlMRNmdqjGU6nqXyZ1kFFqLt+JYlF88E4qC14iy0Q7Sf9koVqEcL RpzqWQU9fxkVSg1vXcWbj0PwCwWzP4MSEiPMk98PNPY79czgTMDV7+Rb1D/J1WnIX9n+ j6nPT6ySXAgu3hJR/w2KGVnorVdwwiq7YuMxap4U1UxC7pm3h14axihS8p4zuPkkpcdO Tdq2Z1Fw3JwGIrh8CwUpHD2FyxhM/gCpxslfYROHYwIFRllxSI+u/NU4Z3IbzEfyf6NB HLJw4hWAK77Wayqu75H7aaZ9ZQyrAwRMB9AMUI7AxVZMI820BOSeNymALyIK1OeOD9cq Awig=="
        ],
        "arc-message-signature": [
            "i=1; a=rsa-sha256; c=relaxed/relaxed; d=google.com; s=arc-20160816; h=to:subject:message-id:date:from:mime-version:dkim-signature; bh=t2DNqkBBJjoLhONZBMPk6xsRZvt4X3Q3zLD2ZS78948=; b=id91bGCitpNDjO5h4nUR11W37vJbw+GLUKADImwgKSxEEXyp/WpH/YbJV/uaZOkbQZ M72udceBDgNeKlxKmHkfJynt1XaPEW00gTFxSCGX6ut4HtgXUUqkPrObPy+UdMWM9YwJ y7oO+J/4n5ecukw+gkGjnxwU5iQ26548nryWnA1ix8lq9CHg04TgDi6+xWS1vkeJg5rb OSpHvwCHnQD7JDNn/i1e3UuPH/VRZJ/PPZwW93k/Ev4pbu24211IPDLb+1k8uGiB7+qG fIi5JCyCYdl8vjpJINNcXAJnxtgLpVQR4+Ki8nWgsYwk6/mrbn2pJb2Qb64Tr51owc5z g4xw=="
        ],
        "arc-authentication-results": [
            "i=1; mx.google.com; dkim=pass header.i=@gmail.com header.s=20161025 header.b=HXMO7C2V; spf=pass (google.com: domain of 0tto.mastr@gmail.com designates 209.85.220.41 as permitted sender) smtp.mailfrom=0tto.mastr@gmail.com; dmarc=pass (p=NONE sp=QUARANTINE dis=NONE) header.from=gmail.com"
        ],
        "return-path": [
            "<0tto.mastr@gmail.com>"
        ],
        "received-spf": [
            "pass (google.com: domain of 0tto.mastr@gmail.com designates 209.85.220.41 as permitted sender) client-ip=209.85.220.41;"
        ],
        "authentication-results": [
            "mx.google.com; dkim=pass header.i=@gmail.com header.s=20161025 header.b=HXMO7C2V; spf=pass (google.com: domain of 0tto.mastr@gmail.com designates 209.85.220.41 as permitted sender) smtp.mailfrom=0tto.mastr@gmail.com; dmarc=pass (p=NONE sp=QUARANTINE dis=NONE) header.from=gmail.com"
        ],
        "dkim-signature": [
            "v=1; a=rsa-sha256; c=relaxed/relaxed; d=gmail.com; s=20161025; h=mime-version:from:date:message-id:subject:to; bh=t2DNqkBBJjoLhONZBMPk6xsRZvt4X3Q3zLD2ZS78948=; b=HXMO7C2VBYbEYwTq9E8lKLkpvN3wm8QDKd00J4XHsp1KuCL+itxOtS6fJ0t3GLI7Dy EHiAa2KnmIlH1rA6L8HMXXsGhn2qqUlfYpE17TK0wsAY7c2e6feyLLDhBDH1T8aHcBFP 8QypUxlxWsPeEGvUsc8k35f1Ibho/DRkhypcfQnOAgcJWklseb8F2tKvM9ypKHHt1Tho p4U9cz/VsTDpGObXWA4rthPm5zLiXx5OmwAlHuqLJgNb0tTg6Mf7J5Q8PWMywbkHUhjO +dNrVHsTnZsJb0iW6rHA7Okci2TBO5jgV4doidAf3kAEBEW//6rzGnsG7+s0ChFML4vw SFTA=="
        ],
        "x-google-dkim-signature": [
            "v=1; a=rsa-sha256; c=relaxed/relaxed; d=1e100.net; s=20161025; h=x-gm-message-state:mime-version:from:date:message-id:subject:to; bh=t2DNqkBBJjoLhONZBMPk6xsRZvt4X3Q3zLD2ZS78948=; b=XaAhCTzM0PnOFn0gguv4efSyQbOPuvb/N4lJ0J7Xlzp8v2ri/kpIJxW9N83dTR3X3Y 6pdmTQC1SbuEn2rPylpbSN4ZN5T5KqyXs+D8Hk8kfa2zBUhAhlbrA0+xYtReK3mZl4+Q mjYEm1t7cvEo/uFEgtJAyyte7aZuPgT/b+vDTZBGBE3ukaFXZSBKNxIg8vCK2YenAIoy nmwdlxtFgkV+ii53qYHr6eKZjHDHWNGg8CQGP5fhcKrrkRHwy0psPDU4hHes8/qd9tFK fFUTTkOny4G3I3KlW95eMW1Ec2GSepCLso+ySFYYg0TCwOec2T2rU8yEhU4diIwWFOb1 9/EQ=="
        ],
        "x-gm-message-state": [
            "APjAAAWYRq9L+4gcjoE3VzuhXbC0pwsJqhs2JFNAuH3T5TmoeMcKo0c4 fRJZKYwz6A6s1JuyBuSN0gCHdVkiomIyB2qC1DXvPA=="
        ],
        "x-google-smtp-source": [
            "APXvYqzpcnzcpBkONSjoHR8b6UayaDVXRE12/d7Z+WK9RTJC5OYOamgmYjUs2iChLCCTAB4BvyrR3gzbHsxtvZlio/Q="
        ],
        "mime-version": [
            "1.0"
        ],
        "from": [
            "Otto Heidebur <0tto.mastr@gmail.com>"
        ],
        "date": [
            "Mon, 3 Feb 2020 19:30:57 -0800"
        ],
        "message-id": [
            "<CAK5jdhJ2a3M-7mYkeSQ9D7Ojhth06SzQT4a_e70SCL-Xpm0g2A@mail.gmail.com>"
        ],
        "subject": [
            "Tttg"
        ],
        "to": [
            "ifchasethenhire@gmail.com"
        ],
        "content-type": [
            "multipart/alternative; boundary=\"000000000000bb4cc7059db7ab45\""
        ]
    }
][{"delivered-to":["ifchasethenhire@gmail.com"],"received":["by 2002:a05:6214:36c:0:0:0:0 with SMTP id t12csp413966qvu; Mon, 3 Feb 2020 20:11:23 -0800 (PST)","from mail80.indeed.com (mail80.indeed.com. [198.58.75.80]) by mx.google.com with ESMTPS id c3si1110670oto.153.2020.02.03.20.11.23 for <ifchasethenhire@gmail.com> (version=TLS1_2 cipher=ECDHE-RSA-AES128-GCM-SHA256 bits=128/128); Mon, 03 Feb 2020 20:11:23 -0800 (PST)","from aus-mexec49.indeed.net (aus-smtp3.indeed.net [10.1.3.212]) by mail80.indeed.com (Postfix) with ESMTP id 48BWTT30tjz5Lp76 for <ifchasethenhire@gmail.com>; Mon,  3 Feb 2020 22:11:09 -0600 (CST)"],"x-google-smtp-source":["APXvYqw4xlmj0yi9g0kFnvdbqGZO3WUi6evdKUa6HG2/3+xWTDz26sRyOxV41XaV4a31ZS/p+P/9"],"x-received":["by 2002:a05:6830:2015:: with SMTP id e21mr19960952otp.106.1580789483698; Mon, 03 Feb 2020 20:11:23 -0800 (PST)"],"arc-seal":["i=1; a=rsa-sha256; t=1580789483; cv=none; d=google.com; s=arc-20160816; b=d4ngPSoBWFOOGUztF1il4eUMbcTx0idZauWRKAILqc7gehiDvHMmg49jHrHmeSpVJw UXDyvxVeYfnaOKgKxYFtgIZUc5JG3e/bsiGc+OqFuoB5ImeOAJ8Fuw55oeccY48jc7TH h3+gR2zgjgZ6D7wqeF+YA2L72wOtbHIJUrDVHr9EZexptAHWxei5ZkROCUYxZ1frHT4C dNjfEEMqvt1LWllyLu7BpmQXAf1a9sM9m1osS4UcVFVpZfnTgCODzramvGrC502GYVg7 6TUc+Zb1ZBlAb+50o4EM3PkPIh6fs38+H+wBahjTKawHpSwp0bpbARJvHcmB+pStG7CZ dIBA=="],"arc-message-signature":["i=1; a=rsa-sha256; c=relaxed/relaxed; d=google.com; s=arc-20160816; h=date:feedback-id:list-unsubscribe:preheader:mime-version:subject :message-id:to:reply-to:from:dkim-signature; bh=MfTKI6hPl1vBtfaOKEZ42mF0ZrI8MSCUgzBMnxpNpOU=; b=FkmVxXbgM4U8762z4Ou1Znjh+qwhim22xsrGHDNr5bvb5+Ucp+CTcSZcZVXmsOo+Jd +WF7+OimiWIDgEYlH6QWPTWq1X0S47s/bpHJvyiOyObfl7SnwX7B3PXVuHBuWl4fUMAw l461ofiFVPFYsmfGV22rqhbTKBwPG+8UsIl2KDI6pvGWGuY1dnAWRyoybOqRbC6qgb0+ hm2J2ieLoWvf116uW9HVrJQaczNl2gA7sCFP1oATqnMf6RPQZ2vTcCigq4DnAw1hfnXj vQPWea9y2KVNWXyYprjVrJKcvsa8KrmSzfooREjuDOCcE/oGckGMIXWyt5GjxyJcPUyM IPUw=="],"arc-authentication-results":["i=1; mx.google.com; dkim=pass header.i=@indeed.com header.s=default header.b=D0HE1shC; spf=pass (google.com: domain of alert@indeed.com designates 198.58.75.80 as permitted sender) smtp.mailfrom=alert@indeed.com; dmarc=pass (p=QUARANTINE sp=QUARANTINE dis=NONE) header.from=indeed.com"],"return-path":["<alert@indeed.com>"],"received-spf":["pass (google.com: domain of alert@indeed.com designates 198.58.75.80 as permitted sender) client-ip=198.58.75.80;"],"authentication-results":["mx.google.com; dkim=pass header.i=@indeed.com header.s=default header.b=D0HE1shC; spf=pass (google.com: domain of alert@indeed.com designates 198.58.75.80 as permitted sender) smtp.mailfrom=alert@indeed.com; dmarc=pass (p=QUARANTINE sp=QUARANTINE dis=NONE) header.from=indeed.com"],"dkim-signature":["v=1; a=rsa-sha256; c=relaxed/simple; d=indeed.com; s=default; t=1580789469; bh=MfTKI6hPl1vBtfaOKEZ42mF0ZrI8MSCUgzBMnxpNpOU=; h=From:Reply-To:To:Subject:List-Unsubscribe:Date; b=D0HE1shC8WFTsvLt8D9pW34BztwkjVVhyAz56cOc1xSGqx6Ctnx+J7u40NmMuap2V 7hKOkiAHnK9cqK/2+4bEhZ6MmCMcP7iUES4DwPjQBblZQQYgDO4yb2xxasP2as8PRi t51OYLxjVphuOLireaHO1QZykcsoDr/FquM/6lqk="],"from":["Indeed <alert@indeed.com>"],"reply-to":["Indeed <do-not-reply@indeed.com>"],"to":["ifchasethenhire@gmail.com"],"message-id":["<1e0769sfqnsrm800.1580789469406.Railgunner@aus-mexec10.indeed.net>"],"subject":["Equation Research is hiring for Junior Software Developer. 5 more junior javascript jobs."],"mime-version":["1.0"],"content-type":["multipart/alternative; boundary=\"----=_Part_157553876_1997228667.1580789469419\""],"preheader":["Apply now at HBS Systems, Equation Research, and Dunham and Company"],"list-unsubscribe":["<mailto:arf-feedback@indeed.com?subject=mailtoTag:5e1bedfc74a1fb386da81b73:JOBALERT:RailgunnerDaemon:1e076a46u27sk801:1e0769sfqnsrm800:indeed.com:2>"],"feedback-id":["JOBALERT:RailgunnerDaemon:Indeed"],"x-indeed-fbl":["5e1bedfc74a1fb386da81b73:2:e901e11e78b40456485d1f3ddd03b030217d355ac31a5ae7bcd96619c43d6f4f"],"x-indeed-client-app":["RailgunnerDaemon"],"x-indeed-content-type":["JOBALERT"],"x-indeed-tk":["1e076a46u27sk801"],"date":["Mon,  3 Feb 2020 22:11:09 -0600 (CST)"]}][{"delivered-to":["ifchasethenhire@gmail.com"],"received":["by 2002:a05:6214:36c:0:0:0:0 with SMTP id t12csp1277010qvu; Tue, 4 Feb 2020 11:22:39 -0800 (PST)","from mail64.indeed.com (mail64.indeed.com. [198.58.75.64]) by mx.google.com with ESMTPS id d197si9828011oig.115.2020.02.04.11.22.38 for <ifchasethenhire@gmail.com> (version=TLS1_2 cipher=ECDHE-RSA-AES128-GCM-SHA256 bits=128/128); Tue, 04 Feb 2020 11:22:39 -0800 (PST)","from aus-mexec81.indeed.net (aus-smtp3.indeed.net [10.1.3.212]) by mail64.indeed.com (Postfix) with ESMTP id 48BvjB2C4vz7R2Zq for <ifchasethenhire@gmail.com>; Tue,  4 Feb 2020 13:22:38 -0600 (CST)"],"x-google-smtp-source":["APXvYqz30NEsq/72Q7gZWIpJ5F6l2ZfgatW6iSWz1pFomfeumY7nI+8vzVA7LcCfYdZsq7a8o8Jx"],"x-received":["by 2002:a9d:6183:: with SMTP id g3mr23027546otk.304.1580844159267; Tue, 04 Feb 2020 11:22:39 -0800 (PST)"],"arc-seal":["i=1; a=rsa-sha256; t=1580844159; cv=none; d=google.com; s=arc-20160816; b=dygWQU3hVeyP595f394Vq0KPHFXPOD4Z+RV9GGCf9sWWeoRSDo+7qyfNOr8g5MdFat Jv+b0h8ypzpa2WzPkeMDXekMXtLItOyZWdKOaJ2GZw7Yf1BXm/e8OaPnqtKsFRJYWQ5Q DwcM5HHJiX88XDS/JNqTJYgQaiH8qKiCKV/QoDmDOYUEeOJZe11lzFbWI3nUmVp5JbvV C6qi4c7slnlHqH9z81D1GQfZepKxbixTIOW2VGXa8O1A8Z3tuTiQFOEzM023zspsNHro tfA8rRIJAU4UFVEDapL9KaVbaIE5DuI5i0DLf8B48phQvVPlAMcB7u2GaUXBYxL0zWWH uOkw=="],"arc-message-signature":["i=1; a=rsa-sha256; c=relaxed/relaxed; d=google.com; s=arc-20160816; h=date:feedback-id:list-unsubscribe:mime-version:subject:message-id :to:reply-to:from:dkim-signature; bh=5ozCkGxMepEBqY5AoIUlqvRYgD22fMxIP2B+7b8FDzA=; b=h4XmyoKKMF1MIdkpNMgypZhZ6Kxf7JOzCoPIBxV14DN/+YMd1ZxW8oYSb5T/rHMKgU 0kErQt6dVS1Ycow8EBj88ideloqdkmpvBE4yQ+KL0L0yghrMPnNDgzByVJOzkYBE8dmC OhyLx6UJB0S3uNgklDdoomYXxvjyox2DoR/2mt95OiS/FZAhGuYrP+bCd16M+AbnrSv2 27ZwQar44RYcDDwJRzXqALcXNYYYlbkhmP4OzY0bpD1NROved+B6n7LfUVjIdaqggDID i0L1HPBYmH+CcEFcplGcWYyb7jQcjFuDdfG57pUcHRVLP8a95JuHCtmNqE5gC2TxL+bf n0jw=="],"arc-authentication-results":["i=1; mx.google.com; dkim=pass header.i=@indeed.com header.s=default header.b=R9zmu7+h; spf=pass (google.com: domain of alert@indeed.com designates 198.58.75.64 as permitted sender) smtp.mailfrom=alert@indeed.com; dmarc=pass (p=QUARANTINE sp=QUARANTINE dis=NONE) header.from=indeed.com"],"return-path":["<alert@indeed.com>"],"received-spf":["pass (google.com: domain of alert@indeed.com designates 198.58.75.64 as permitted sender) client-ip=198.58.75.64;"],"authentication-results":["mx.google.com; dkim=pass header.i=@indeed.com header.s=default header.b=R9zmu7+h; spf=pass (google.com: domain of alert@indeed.com designates 198.58.75.64 as permitted sender) smtp.mailfrom=alert@indeed.com; dmarc=pass (p=QUARANTINE sp=QUARANTINE dis=NONE) header.from=indeed.com"],"dkim-signature":["v=1; a=rsa-sha256; c=relaxed/simple; d=indeed.com; s=default; t=1580844158; bh=CdawW7IQmM88WBdiWyP6UEVeLOuYwOgRpwj0HrnTTvw=; h=From:Reply-To:To:Subject:List-Unsubscribe:Date; b=R9zmu7+hMW1N6sf/075vcWr8B/9iJYPdstm3qui46CxiCNcIi6TjpaFClhld/cofu togzf2JntmqbASQ3DSC3w6mRF3pBezXK3Ky6BXXhD0F4khbmICy2mqPlrTzUC88lj5 OiCckLVQv6Gn2K/D9ZWN0dfzGnX+jz9IepAstpa0="],"from":["Indeed <alert@indeed.com>"],"reply-to":["Indeed <do-not-reply@indeed.com>"],"to":["ifchasethenhire@gmail.com"],"message-id":["<1e08m8dd8nhu6808.1580844158280.Railgunner@aus-mexec127.indeed.net>"],"subject":["Your job alert for node​.js remote is now active"],"mime-version":["1.0"],"content-type":["multipart/alternative; boundary=\"----=_Part_44780772_649401.1580844158309\""],"list-unsubscribe":["<https://subscriptions.indeed.com/alerts/cancel?token=CkBQmf7iboR-MU6YJ6IUfuheEd73LXCmR3HmHJEXFW6gMhiv-xtMBKmA6HTpGJBmTyhmLAzVbP4iZhV6dxs05x_0EiBwXCu43-1gfBi1B2pdWpYoXeXq-Bm93v0DVTz3DCjf2BoQyMx6xU16Yj559mxZ3k3TOg%3D%3D&co=US&hl=en&tmtk=1e08m8dd8nhu6808&subId=5e39b340a90a5324211bcaf9&rgtk=1e08qf37snu78803&from=listunsub>"],"feedback-id":["JOBALERT_WELCOME:RailgunnerDaemon:Indeed"],"x-indeed-fbl":[":2:e901e11e78b40456485d1f3ddd03b030217d355ac31a5ae7bcd96619c43d6f4f"],"x-indeed-client-app":["RailgunnerDaemon"],"x-indeed-content-type":["JOBALERT_WELCOME"],"x-indeed-tk":["1e08qf3a8nu78801"],"date":["Tue,  4 Feb 2020 13:22:38 -0600 (CST)"]}][{"delivered-to":["ifchasethenhire@gmail.com"],"received":["by 2002:a05:6214:36c:0:0:0:0 with SMTP id t12csp1580279qvu; Tue, 4 Feb 2020 17:16:10 -0800 (PST)","from o5.sgmail.github.com (o5.sgmail.github.com. [192.254.113.10]) by mx.google.com with ESMTPS id n14si508936edq.409.2020.02.04.17.16.09 for <ifchasethenhire@gmail.com> (version=TLS1_2 cipher=ECDHE-RSA-AES128-GCM-SHA256 bits=128/128); Tue, 04 Feb 2020 17:16:10 -0800 (PST)","by filter1387p1mdw1.sendgrid.net with SMTP id filter1387p1mdw1-13292-5E3A1758-14 2020-02-05 01:16:08.49282857 +0000 UTC m=+352308.675412413","from github-lowworker-2ef7ba1.ac4-iad.github.net (unknown [140.82.115.13]) by ismtpd0023p1iad2.sendgrid.net (SG) with ESMTP id 3nbDK8zcTdOiA1wNJ0mtxw Wed, 05 Feb 2020 01:16:08.356 +0000 (UTC)","from github.com (localhost [127.0.0.1]) by github-lowworker-2ef7ba1.ac4-iad.github.net (Postfix) with ESMTP id 1AACF180782; Tue,  4 Feb 2020 17:16:08 -0800 (PST)"],"x-google-smtp-source":["APXvYqxQ3g2aX3rkPS4erSdjAOnq6mlGn9brd/1CKNAIYHPfyZVvfgxbGb182CU7Ch4RYtZCaRc1"],"x-received":["by 2002:aa7:c3c8:: with SMTP id l8mr2750470edr.122.1580865370754; Tue, 04 Feb 2020 17:16:10 -0800 (PST)"],"arc-seal":["i=1; a=rsa-sha256; t=1580865370; cv=none; d=google.com; s=arc-20160816; b=NfG+/Bzh1aE4a3R3ArGa7V5hAW7n0VFSSRxPGNQfiXwBS79yxXvQvnBwfSqpS3/U3H R4Gf3tH0aocelN3l//2rRHPE5g+wHG4+Cgiwd/SR5f+0RfVNZ4gOtw2npQaZNEuMyElF JMb3Nc3207GIKXsQQqA0MkFu4hyneCVtjYypi/IKU+WImyjKPQM0HP+B9/jyS2EnZ3p3 P9SsEHeYU6EB6uEDE+kruGl9mQ8ib6HGGk/gCIwNKpbyHmYQpzGC89RKDto1Ez2iEG4w MKWr+NXR4iN14hBEEPVp75Rg2xb6Rx470sAz8zc/Avz2dg0iAnafYntDRjheBJppFMa2 RxRA=="],"arc-message-signature":["i=1; a=rsa-sha256; c=relaxed/relaxed; d=google.com; s=arc-20160816; h=categories:content-transfer-encoding:mime-version:subject :message-id:to:from:date:dkim-signature:dkim-signature; bh=gjOamcM2jkEmglbneSwor60Gf74ouXm3q3p4qNrS/9k=; b=dqFj+eyynvH4EAOIZEIA/XjByCieMdXPT5OYLw3OsSTzuGvR8nb780T6OPsqH9Hn5C vQGlWRrBcVhT+ILkAzUv3oZmUl8hjq/eL/f/EbSa0at8ELGbCTqUHNcM01P51rY4Giiy hfXBCRSXQYNL68zt3leE91brRuV3EFKcrKFGj+wChLMJoPvtI0VnfTkzj2F+y/9qLzk7 9YvIo9/T8urvUx3oufpNkFmTsH8GylZW/ykOUxlJD0Aw5/MqdWkMRrBkrRVSQkW5FRt9 CYk03MzBKUnH1vQUDSgj4C8px7r6O2mHOIoEC3Xj2V3aDzIHcoDZ/t4qJOdG5WjV8VyH bfOw=="],"arc-authentication-results":["i=1; mx.google.com; dkim=pass header.i=@github.com header.s=s20150108 header.b=k9vatWS7; dkim=pass header.i=@sendgrid.info header.s=smtpapi header.b=BUn7qAtP; spf=pass (google.com: domain of bounces+848413-9607-ifchasethenhire=gmail.com@sgmail.github.com designates 192.254.113.10 as permitted sender) smtp.mailfrom=\"bounces+848413-9607-ifchasethenhire=gmail.com@sgmail.github.com\"; dmarc=pass (p=NONE sp=NONE dis=NONE) header.from=github.com"],"return-path":["<bounces+848413-9607-ifchasethenhire=gmail.com@sgmail.github.com>"],"received-spf":["pass (google.com: domain of bounces+848413-9607-ifchasethenhire=gmail.com@sgmail.github.com designates 192.254.113.10 as permitted sender) client-ip=192.254.113.10;"],"authentication-results":["mx.google.com; dkim=pass header.i=@github.com header.s=s20150108 header.b=k9vatWS7; dkim=pass header.i=@sendgrid.info header.s=smtpapi header.b=BUn7qAtP; spf=pass (google.com: domain of bounces+848413-9607-ifchasethenhire=gmail.com@sgmail.github.com designates 192.254.113.10 as permitted sender) smtp.mailfrom=\"bounces+848413-9607-ifchasethenhire=gmail.com@sgmail.github.com\"; dmarc=pass (p=NONE sp=NONE dis=NONE) header.from=github.com"],"dkim-signature":["v=1; a=rsa-sha256; c=relaxed/relaxed; d=github.com; h=from:to:subject:mime-version:content-type:content-transfer-encoding; s=s20150108; bh=gjOamcM2jkEmglbneSwor60Gf74ouXm3q3p4qNrS/9k=; b= k9vatWS7JOACyMoWIAZhX5qJFu6yzABw4PgJz9eYIBpTxKQj5Xmu/kaBt6KVJqHd uL4DwTfJfGoEp7Nyt+UoEq5Ir2SjMdEQOSLedCPElKcaA/YF2AshGSos3yz8eKJz gfI+aRVYpBg74cJ9CqgSl1lDR1cqgx/6P3aKR2Sktow=","v=1; a=rsa-sha256; c=relaxed/relaxed; d=sendgrid.info; h=from:to:subject:mime-version:content-type:content-transfer-encoding:x-feedback-id; s=smtpapi; bh=gjOamcM2jkEmglbneSwor60Gf74ouXm3q3p4qNrS/9k=; b=BU n7qAtPwSQ2gE+TAeC8QrAzia34jRU4qGFoP190G2mWSGqIfP3JGjUDvQbg6KkOZD Ms18ho/KnS+anLV16Inm5aKKaDjzv/aZmH8jqOY4rrkQ5DVCYsR/7l0fNlvIo8/H ITVzdTU81W4/gQUNfzECyDx+JNb7KqMkCg1RNvgCo="],"date":["Wed, 05 Feb 2020 01:16:08 +0000 (UTC)"],"from":["GitHub <noreply@github.com>"],"to":["cheidebur <spekter.x@gmail.com>"],"message-id":["<5e3a175819f9e_49603f87222cd95c550ed@github-lowworker-2ef7ba1.ac4-iad.github.net.mail>"],"subject":["[GitHub] A third-party OAuth application has been added to your account"],"mime-version":["1.0"],"content-type":["text/plain; charset=UTF-8"],"content-transfer-encoding":["7bit"],"x-auto-response-suppress":["All"],"categories":["account-security,new-oauth-authorization"],"x-sg-eid":["1lu6SIF4WSwa0DaFwyLhTcTp+f5SGVRqGv0oM04PbxXFV2U00IfN28QbLVlvlyCY13Qv0Lwos4Ax9M dR64taOfbdeyyvWKcNcQkqxHFcIgK89Yt5+EVxjBOpfKsEZVUIZmrC/t59ZAZ6+NWEIi34so6Ly6ts /EmuxC77VHACWpU29oIJQl2wqgzcZnbcq37lDEMIZBT2sJDIGuPvxXA4CA=="],"x-sg-id":["HjuyJHjWedrv+ZABmVoKqJUGcbnIrpG8Dl8TZw63o/tYHvHAZuj7fE3sBkCPSNz92pSnrCLqO00MaT UToqoVhg=="],"x-feedback-id":["848413:6xvVEJqleZlAW7/vhv7PzD/cv5tamo2SWZDKyvugGvg=:/tVyTrc5pGf9LyskfwdeL8MHpmfxmY45w4+vOgpL1lE=:SG"]}][{"delivered-to":["ifchasethenhire@gmail.com"],"received":["by 2002:a05:6214:36c:0:0:0:0 with SMTP id t12csp171497qvu; Tue, 4 Feb 2020 21:43:30 -0800 (PST)","from mail90.indeed.com (mail90.indeed.com. [198.58.75.90]) by mx.google.com with ESMTPS id 105si13151575otu.45.2020.02.04.21.43.29 for <ifchasethenhire@gmail.com> (version=TLS1_2 cipher=ECDHE-RSA-AES128-GCM-SHA256 bits=128/128); Tue, 04 Feb 2020 21:43:30 -0800 (PST)","from aus-mexec110.indeed.net (aus-smtp1.indeed.net [10.1.3.210]) by mail90.indeed.com (Postfix) with ESMTP id 48C9TX6wcbz34jm for <ifchasethenhire@gmail.com>; Tue,  4 Feb 2020 23:43:28 -0600 (CST)"],"x-google-smtp-source":["APXvYqwUqUQBsHTYcYIhOF6IxITHDzE5l8JaaF8T8iPuxCIZZNi9CIKHCXHt/UFr7ijq4WcqGQZw"],"x-received":["by 2002:aca:1c01:: with SMTP id c1mr1833242oic.18.1580881410399; Tue, 04 Feb 2020 21:43:30 -0800 (PST)"],"arc-seal":["i=1; a=rsa-sha256; t=1580881410; cv=none; d=google.com; s=arc-20160816; b=BWjdsCjNRL7PRHEhjFJXDAAClA44hl9RKF/C03CGBczJ7bZHmZWBW7cV+ZIrNlWP/O PmdQZ1q2mOi6X4ZmPAQehtdfDMxmFR0j5FwDTqgZHtKiQVLTKegCfHqfhM7IHMooQ+Xu KV4/O7ev5I400wVQah5JPIIV5WVAqkUCd4UAbtpP0Xda1tBhNHtTxO5eYzpLACa7GI11 gaZWMzSS5yY1W40sWPs0qs/ox2tLiOQW6h77Nuspv5AbJqJKkfBGLoEhioK8xzQcbGdI fkhnV8Yv7QZQ7UCvSdsRwN5pHVANy1Lv52YbpM+0e3ReELZG5gazUKSOgjxqla4JCKfn ghWg=="],"arc-message-signature":["i=1; a=rsa-sha256; c=relaxed/relaxed; d=google.com; s=arc-20160816; h=date:feedback-id:list-unsubscribe:preheader:mime-version:subject :message-id:to:reply-to:from:dkim-signature; bh=VG2bGFlS02mhzeM7Oodqye3VU0H743aXk0YK4wdBANE=; b=zBECtekbA8Sri16rqokwaS+o1qPcVYwhVDC5kiVde7D4yO4KrMtSVLS9P3UPI76VD5 bKCMomXNK9NzPDrim2XXzK1uTEY2alPulmnrLcsteQIvKgX3Xd4zZrI+dKJOC+7/Bqqk oa1XP1AFk24jRBitj5H3HH0fGMBmFUp4rqxsTOlksCsNEHM0Ld8o2eHLwKe46pV4sf4i JWKLRr5mnPp4Kyu+a0/tjqwjtOCENRBB4jFsVqCeQgNFnVCUxMg2dKh7fGYv3KRROloA 7we798wMTBPykya4S98jkdEZXH0/O8G3qpHHv9I/uVTw2BHgXbSsk2uO1otkUmqa5mus nl4g=="],"arc-authentication-results":["i=1; mx.google.com; dkim=pass header.i=@indeed.com header.s=default header.b=QQqBKJG8; spf=pass (google.com: domain of alert@indeed.com designates 198.58.75.90 as permitted sender) smtp.mailfrom=alert@indeed.com; dmarc=pass (p=QUARANTINE sp=QUARANTINE dis=NONE) header.from=indeed.com"],"return-path":["<alert@indeed.com>"],"received-spf":["pass (google.com: domain of alert@indeed.com designates 198.58.75.90 as permitted sender) client-ip=198.58.75.90;"],"authentication-results":["mx.google.com; dkim=pass header.i=@indeed.com header.s=default header.b=QQqBKJG8; spf=pass (google.com: domain of alert@indeed.com designates 198.58.75.90 as permitted sender) smtp.mailfrom=alert@indeed.com; dmarc=pass (p=QUARANTINE sp=QUARANTINE dis=NONE) header.from=indeed.com"],"dkim-signature":["v=1; a=rsa-sha256; c=relaxed/simple; d=indeed.com; s=default; t=1580881409; bh=VG2bGFlS02mhzeM7Oodqye3VU0H743aXk0YK4wdBANE=; h=From:Reply-To:To:Subject:List-Unsubscribe:Date; b=QQqBKJG88WH8zCPxUICWpS0yxU37O4Ras+p14MOlR5MjMLsRrX/w9gzkoR0wAPyCQ 4s1XNTivbOWUZ5yg4Qj9MCi9szzj4zzHZ0IsQdezHFo3rduXucaH+BDSJSygolLoUD IJ9VipMnJvc+p9r2F67E/yLw3pXeK3YQsEzqtKgU="],"from":["Indeed <alert@indeed.com>"],"reply-to":["Indeed <do-not-reply@indeed.com>"],"to":["ifchasethenhire@gmail.com"],"message-id":["<1e09tvsqfnsrm800.1580881408961.Railgunner@aus-mexec87.indeed.net>"],"subject":["Equation Research is hiring for Junior Software Developer. 9 more junior javascript jobs."],"mime-version":["1.0"],"content-type":["multipart/alternative; boundary=\"----=_Part_28546767_1673284334.1580881408971\""],"preheader":["Apply now at Gruen Agency, Chatman Design, and Equation Research"],"list-unsubscribe":["<mailto:arf-feedback@indeed.com?subject=mailtoTag:5e1bedfc74a1fb386da81b73:JOBALERT:RailgunnerDaemon:1e09tvsu23hh0800:1e09tvsqfnsrm800:indeed.com:2>"],"feedback-id":["JOBALERT:RailgunnerDaemon:Indeed"],"x-indeed-fbl":["5e1bedfc74a1fb386da81b73:2:e901e11e78b40456485d1f3ddd03b030217d355ac31a5ae7bcd96619c43d6f4f"],"x-indeed-client-app":["RailgunnerDaemon"],"x-indeed-content-type":["JOBALERT"],"x-indeed-tk":["1e09tvsu23hh0800"],"date":["Tue,  4 Feb 2020 23:43:28 -0600 (CST)"]}][{"delivered-to":["ifchasethenhire@gmail.com"],"received":["by 2002:a05:6214:36c:0:0:0:0 with SMTP id t12csp415116qvu; Wed, 5 Feb 2020 02:44:11 -0800 (PST)","from mail-sor-f69.google.com (mail-sor-f69.google.com. [209.85.220.69]) by mx.google.com with SMTPS id q9sor14000637oic.174.2020.02.05.02.44.10 for <ifchasethenhire@gmail.com> (Google Transport Security); Wed, 05 Feb 2020 02:44:11 -0800 (PST)","by 2002:aca:f08:: with SMTP id 8mr2889754oip.60; Wed, 05 Feb 2020 02:44:10 -0800 (PST)"],"x-received":["by 2002:aca:cf52:: with SMTP id f79mr2465679oig.129.1580899451136; Wed, 05 Feb 2020 02:44:11 -0800 (PST)","by 2002:aca:f08:: with SMTP id 8mr2492254oip.60.1580899450891; Wed, 05 Feb 2020 02:44:10 -0800 (PST)"],"arc-seal":["i=1; a=rsa-sha256; t=1580899451; cv=none; d=google.com; s=arc-20160816; b=KYiRwwS4H07wbv5lWmO6KU2jPsCeivT0FlU0+yRF5qD5O+muOXC7hYAIaaX4onAoLg e+u/mrHyvTqCocPRVjkBmCh6OlZc+E4XuDbVXqyi/uJUKMwwIEHGnQQNpXRuCZhWT8jM NX276r2z8BPQ9yrcKTDK+l9Zp8dB/ODek4IKXsuIwyE0dj7Ge2EjlDwm29h8UOphvj3U 7jWi7NwrXvVRGxe7w3bz6567VaY3IEPp9Rrff7S6/XrB5z44+4tBKbp1aOzgw7G15+hq nPSZo8rd0NZHxRsfaEEf0hBfluhx98eVQ+7UWOXQP0nmdoHLVQ7IcipLgFAAYwGzlGCu Humw=="],"arc-message-signature":["i=1; a=rsa-sha256; c=relaxed/relaxed; d=google.com; s=arc-20160816; h=in-reply-to:references:subject:from:date:message-id:auto-submitted :to:dkim-signature; bh=EkPg0Ucua4/9nDTTxk/7xEryTOV1sdigtmiB1FPku7U=; b=w4j6NODMTs9yb4F11NdKiJR/WbZUt4UfINN1L67sfsPlXo2BjPxdRGSFTpFS1+xURR hVBBJd+/EKd5h/EI0px9Q0vK4TWtzxLXwTeY84sD+K8OkMU9y/MPlXNveqdiXzC71TU0 /h61UCgFvrpxgxWJagVvUIWU1kflTb6q8yWFmxmFNMEI7rAv3FdztbAMusS5JaIfsHAD X2d6v+WWKEPlNb2cum85mlhH5nolqdzzPGru5mliaUwwPLt9gjFeSgjIeblHiGt/Tscm bcsxwvBUQrdOw41hqZo75Sn4X4/WOeUBo/S0NugbGOd0F0D3jD+ezg9EIdsmlbGMvAAl YIdg=="],"arc-authentication-results":["i=1; mx.google.com; dkim=pass header.i=@googlemail.com header.s=20161025 header.b=TQOoqicd; spf=pass (google.com: best guess record for domain of postmaster@mail-sor-f69.google.com designates 209.85.220.69 as permitted sender) smtp.helo=mail-sor-f69.google.com; dmarc=pass (p=QUARANTINE sp=QUARANTINE dis=NONE) header.from=googlemail.com"],"return-path":["<>","<>"],"received-spf":["pass (google.com: best guess record for domain of postmaster@mail-sor-f69.google.com designates 209.85.220.69 as permitted sender) client-ip=209.85.220.69;"],"authentication-results":["mx.google.com; dkim=pass header.i=@googlemail.com header.s=20161025 header.b=TQOoqicd; spf=pass (google.com: best guess record for domain of postmaster@mail-sor-f69.google.com designates 209.85.220.69 as permitted sender) smtp.helo=mail-sor-f69.google.com; dmarc=pass (p=QUARANTINE sp=QUARANTINE dis=NONE) header.from=googlemail.com"],"dkim-signature":["v=1; a=rsa-sha256; c=relaxed/relaxed; d=googlemail.com; s=20161025; h=to:auto-submitted:message-id:date:from:subject:references :in-reply-to; bh=EkPg0Ucua4/9nDTTxk/7xEryTOV1sdigtmiB1FPku7U=; b=TQOoqicdwGdazzhz9dyQ1+Yu/CAbZaLddMc4p5Z1nICS/7a1C32PlV18/HkELQPNTL BYtIywhyAMFQdv52/Q8zmnSR3KqDO1F8l34iY1tX4AnakdlZQCSZlfqYiDE7/V/02al/ xhmOQ8JHcb+jV4w4qwHthwOqIwOcAqjz9SW2cdqFXQJSLP8fEMt7SzaRzh3PAEZ4A+tP Aplxf1W1NW9tztmZwxUFckRwCQkcoCRxaTYfmwRaiYmACEkl0u6gi9tkNWrWtcT+1FYr gppN75k1wQgF4DM5CEHn0i01gALPrvLSyDd6xLDbuvlUx9EHyMhvxnE9waXqRE62b8rR FFVA=="],"x-google-dkim-signature":["v=1; a=rsa-sha256; c=relaxed/relaxed; d=1e100.net; s=20161025; h=x-gm-message-state:to:auto-submitted:message-id:date:from:subject :references:in-reply-to; bh=EkPg0Ucua4/9nDTTxk/7xEryTOV1sdigtmiB1FPku7U=; b=r3ISO4UZ8Ukk6lNyJ9t+whP4cBdEphSO6MOmU06WFWA4e30YMvKjZWHAZGsJrVe5De AOKe8P2ZuJp6mu2h9GlMBdMv8wjy+pGQdE1Jvb900c8oJWbl1j7JG9nuHRe01bscTqzq ljShy3vQ63gnDK8B8RTlopLm5kjVT9N+jn3sSpNxzIaOEyjuy5KqsBOy0gKStGiKfSSx KCZwem5DEA94owWvUwFY29c1qw3ieBlPx/Wo+z4R5Jm9eVg5fxWMaVUsA9AvDDZ+YvxS jOy7Tj8SPr32ugZLy4L9MbIkeAaHsBtbcbeq821NCCaKV6CtpVpzFuEeTWLy5QWMebcy KvYA=="],"x-gm-message-state":["APjAAAWZbwQ/v/JwzGoQzOtNCa5S4GH0rb6tWgv/RccV8MCvjp7CAQVr 9q2jThlQqCfKTihueP7r93xNd/QU7Zw7sxsj1hbyyQ=="],"x-google-smtp-source":["APXvYqwXJnwlFwe/gd25fICrH5XdXSgv8CO5n33GhOUyjtd9groYYWi6Twb9JrgD3Nibt0LVSQmMTLzF29uZkv9oych2OJfp+Dn9Rm8="],"content-type":["multipart/report; boundary=\"000000000000321079059dd1d6d0\"; report-type=delivery-status"],"to":["ifchasethenhire@gmail.com"],"auto-submitted":["auto-replied"],"message-id":["<5e3a9c7a.1c69fb81.151d6.0e0e.GMR@mx.google.com>"],"date":["Wed, 05 Feb 2020 02:44:10 -0800 (PST)"],"from":["Mail Delivery Subsystem <mailer-daemon@googlemail.com>"],"subject":["Delivery Status Notification (Failure)"],"references":["<027920a2-78f6-495f-1919-9da55b2e633d@gmail.com>"],"in-reply-to":["<027920a2-78f6-495f-1919-9da55b2e633d@gmail.com>"],"x-failed-recipients":["noreply@github.com"]}][{"delivered-to":["ifchasethenhire@gmail.com"],"received":["by 2002:a05:6214:36c:0:0:0:0 with SMTP id t12csp76494qvu; Wed, 5 Feb 2020 22:03:50 -0800 (PST)","from mail70.indeed.com (mail70.indeed.com. [198.58.75.70]) by mx.google.com with ESMTPS id 10si1546619ois.76.2020.02.05.22.03.49 for <ifchasethenhire@gmail.com> (version=TLS1_2 cipher=ECDHE-RSA-AES128-GCM-SHA256 bits=128/128); Wed, 05 Feb 2020 22:03:50 -0800 (PST)","from aus-mexec91.indeed.net (aus-smtp2.indeed.net [10.1.3.211]) by mail70.indeed.com (Postfix) with ESMTP id 48CntY59Gcz5H7 for <ifchasethenhire@gmail.com>; Thu,  6 Feb 2020 00:03:49 -0600 (CST)"],"x-google-smtp-source":["APXvYqybsLJHoPTR7qv6V7Jc3MvnMpfT+rAKJ+XACiys+dfy4jn3WnG/Y7taPYqWTEA2g51DdcaO"],"x-received":["by 2002:a9d:6b84:: with SMTP id b4mr29751165otq.190.1580969030233; Wed, 05 Feb 2020 22:03:50 -0800 (PST)"],"arc-seal":["i=1; a=rsa-sha256; t=1580969030; cv=none; d=google.com; s=arc-20160816; b=HJ61IBloVVNn8qAzRNSwELpAxxtvW5pP9B0aZL/iWkzZ4GDb6Y5+eI4HHZQpoo/EGW kRfjBAdWT/xw0bCFzKUU5zXkQ9DesNYI+/BiTQ6Iw92KxEIvcReTqq/X33CedSPHpDyn PZArSB4aHv+T83ymeZOYVqkuTGsm2NsWe+ydDbXqjO9kOAVLYCKwWOjMrCEehLRGtTCs wqSJNryHTZX6HpPcHMgYS3Y8YUQ6VFdRy+DecWQlEX1oBapTg5ruxDLHe0DrNEuMoX7Z J+oHcaRSRJvGntdAkwWzdmSKa9oHr0jXdtArET4qGULKBMcNOeRbf7fL2LlTCM9VAF68 NZCQ=="],"arc-message-signature":["i=1; a=rsa-sha256; c=relaxed/relaxed; d=google.com; s=arc-20160816; h=date:feedback-id:list-unsubscribe:preheader:mime-version:subject :message-id:to:reply-to:from:dkim-signature; bh=CGwUdT06KISjFh3W72Zu7uv10g5bWsomX3I8Q3RW3Ok=; b=jiOdtPFe9GYuu28TmRd7jxqO5MVsl8oILInh4QUGBJsuy0vdGRrXnlrBeXZMLnkvTo UirjwVXOVMuWqLxqepVOO3yWlUJQ0TTA2CRez71V5AEGc9DoXcuCKpAdOiiYZjacrkav rf73oMk9QbKZokxs1toG4fYv0j3TbAmIbHKIV0n4E+/8de8zYPZLGNUMaxz/FjQfsyPF O7Whtd+/6e6+wLWYHWQAglbE29t5rrIEI0BlfVyTCG16JsQR2+Y9zXjw8TvnxEKQ+CDl qGzqHmA09sSuib/JeEKtPMAYVg3sdKXpDPGEog489+l5p+zv1rufawcvM2Ws6ZM1sTby 5w9w=="],"arc-authentication-results":["i=1; mx.google.com; dkim=pass header.i=@indeed.com header.s=default header.b=\"m/MskB4B\"; spf=pass (google.com: domain of alert@indeed.com designates 198.58.75.70 as permitted sender) smtp.mailfrom=alert@indeed.com; dmarc=pass (p=QUARANTINE sp=QUARANTINE dis=NONE) header.from=indeed.com"],"return-path":["<alert@indeed.com>"],"received-spf":["pass (google.com: domain of alert@indeed.com designates 198.58.75.70 as permitted sender) client-ip=198.58.75.70;"],"authentication-results":["mx.google.com; dkim=pass header.i=@indeed.com header.s=default header.b=\"m/MskB4B\"; spf=pass (google.com: domain of alert@indeed.com designates 198.58.75.70 as permitted sender) smtp.mailfrom=alert@indeed.com; dmarc=pass (p=QUARANTINE sp=QUARANTINE dis=NONE) header.from=indeed.com"],"dkim-signature":["v=1; a=rsa-sha256; c=relaxed/simple; d=indeed.com; s=default; t=1580969029; bh=CGwUdT06KISjFh3W72Zu7uv10g5bWsomX3I8Q3RW3Ok=; h=From:Reply-To:To:Subject:List-Unsubscribe:Date; b=m/MskB4BaztI9+fzuduyzQTcwimcMboqw6bP/ClLqwzSaHVvTQkjYXF8VgEvu5IA0 //hgEYCGKjRC5xh0HJ3hmcEWpsDiMHSP4JxZzC23K0CIisQESaquVMU7DGXQ7B8aDE GGKu59a6BlqA7HvTVvYR8OF+v0mSKC8T0hrq4Co4="],"from":["Indeed <alert@indeed.com>"],"reply-to":["Indeed <do-not-reply@indeed.com>"],"to":["ifchasethenhire@gmail.com"],"message-id":["<1e0chhrvbnsrm801.1580969029712.Railgunner@aus-mexec117.indeed.net>"],"subject":["Vermont Information Processing is hiring for Junior iOS Application Developer. 16 more junior javascript jobs."],"mime-version":["1.0"],"content-type":["multipart/alternative; boundary=\"----=_Part_224628145_243624648.1580969029724\""],"preheader":["Apply now at MassMutual, Cox Automotive, and CommScope"],"list-unsubscribe":["<mailto:arf-feedback@indeed.com?subject=mailtoTag:5e1bedfc74a1fb386da81b73:JOBALERT:RailgunnerDaemon:1e0chhs2h3psm800:1e0chhrvbnsrm801:indeed.com:2>"],"feedback-id":["JOBALERT:RailgunnerDaemon:Indeed"],"x-indeed-fbl":["5e1bedfc74a1fb386da81b73:2:e901e11e78b40456485d1f3ddd03b030217d355ac31a5ae7bcd96619c43d6f4f"],"x-indeed-client-app":["RailgunnerDaemon"],"x-indeed-content-type":["JOBALERT"],"x-indeed-tk":["1e0chhs2h3psm800"],"date":["Thu,  6 Feb 2020 00:03:49 -0600 (CST)"]}][{"delivered-to":["ifchasethenhire@gmail.com"],"received":["by 2002:a05:6214:36c:0:0:0:0 with SMTP id t12csp358304qvu; Thu, 6 Feb 2020 03:27:43 -0800 (PST)","from mail-sor-f69.google.com (mail-sor-f69.google.com. [209.85.220.69]) by mx.google.com with SMTPS id b11sor3080878pls.3.2020.02.06.03.27.43 for <ifchasethenhire@gmail.com> (Google Transport Security); Thu, 06 Feb 2020 03:27:43 -0800 (PST)","by 2002:a17:902:9691:: with SMTP id n17mr2850449plp.304; Thu, 06 Feb 2020 03:27:43 -0800 (PST)"],"x-received":["by 2002:a17:90a:8547:: with SMTP id a7mr3890120pjw.0.1580988463570; Thu, 06 Feb 2020 03:27:43 -0800 (PST)","by 2002:a17:902:9691:: with SMTP id n17mr3284107plp.304.1580988463070; Thu, 06 Feb 2020 03:27:43 -0800 (PST)"],"arc-seal":["i=1; a=rsa-sha256; t=1580988463; cv=none; d=google.com; s=arc-20160816; b=oGHafXe/Cs+ZfxRzErJqo8lVv/+8o1Jn2MKMkv3Hf9WtbVIrZud5+UZl3OsEnuM05Y o+tRBHUp9IyVr1c7gv4cntYDkmy9nmLftDTTHo7+YW8crKG3HufGQyOamzWFUtdnMMRw nLBeB1PdaPLpGutKhMGrER5Mn3AF8o40W9pVkY8RmWncCf7EN7R/mUKYlylHsN56gO6H Aw2Cf7LtGmI4no7tfGWpKuZP6ZgS8GH2tC9EMj7TidpvcarIk9qnhKCAqj29SuZGgAGw T71F3Bym/5klJiFew0AHQPNoCTpBq2rlG6czJpvCBLL3BMDyZspf3Lx7WgBWcdPp0CzX dd8w=="],"arc-message-signature":["i=1; a=rsa-sha256; c=relaxed/relaxed; d=google.com; s=arc-20160816; h=in-reply-to:references:subject:from:date:message-id:auto-submitted :to:dkim-signature; bh=XQn9OkLmErA/tAilD7UbDGhZArjQ5DDbS8Ki23X/v58=; b=bJ3aRcNsJBwI0q0tcpLu10cE1/DO23n1VOJHG8bNhK6MlaAjL4jbARVZbG7r6qVT6v 6Pe5wNFKHYq2jA6qVSIVfEkjm3AlybVWgLgDATO8qGGZ45JYU67pTLCxoCh9Cf+9cVjt 1OQKHteyeECK8K/r8MbakQar1G4jkw939VuDbCfQ5zcSTO2xWMXaOFKYzcbglGc1A8u+ le5h90aKojiJPyUhG89DU8qBb15+ZHy7T5FZMkLBMMVICvzEXIkd6I6d1rnt9un9mQSw yvulEe4C+Z74znhm/6F4y/nXsk8/9eyHlkLL5IE5BAdvZVLDKWO4ymxuMeTTMd17Pem+ 1qVw=="],"arc-authentication-results":["i=1; mx.google.com; dkim=pass header.i=@googlemail.com header.s=20161025 header.b=ta4rQjE9; spf=pass (google.com: best guess record for domain of postmaster@mail-sor-f69.google.com designates 209.85.220.69 as permitted sender) smtp.helo=mail-sor-f69.google.com; dmarc=pass (p=QUARANTINE sp=QUARANTINE dis=NONE) header.from=googlemail.com"],"return-path":["<>","<>"],"received-spf":["pass (google.com: best guess record for domain of postmaster@mail-sor-f69.google.com designates 209.85.220.69 as permitted sender) client-ip=209.85.220.69;"],"authentication-results":["mx.google.com; dkim=pass header.i=@googlemail.com header.s=20161025 header.b=ta4rQjE9; spf=pass (google.com: best guess record for domain of postmaster@mail-sor-f69.google.com designates 209.85.220.69 as permitted sender) smtp.helo=mail-sor-f69.google.com; dmarc=pass (p=QUARANTINE sp=QUARANTINE dis=NONE) header.from=googlemail.com"],"dkim-signature":["v=1; a=rsa-sha256; c=relaxed/relaxed; d=googlemail.com; s=20161025; h=to:auto-submitted:message-id:date:from:subject:references :in-reply-to; bh=XQn9OkLmErA/tAilD7UbDGhZArjQ5DDbS8Ki23X/v58=; b=ta4rQjE9LDxL73VsxpTz2Ewod8ubMZIcgFHRTUcaU/6rLWNcxegy3m+V7lgm6D/Vu4 tfjdrXaI2yp+BTAOvZ3EN8RYIwG4SsOHun65cVUv7B5hFwpDOTWzOQH3VKD/tHQ4c7y1 qGO0jL2F5LlxQuxATKwlsX7netS0FRmViKiwFNgllwMP1eiQtz4wUjmgKgD9R4UprgzJ Vqr4FqC1SutZ3FCkS5VOoa/BD2ZISUgSapCk0TJPvP4LK06ytoSeEH3YKdFyE3HFQQVP DWwivTbJGJLbJnRqZ7oJic5z2H2Q/I4OpuJYB0+G7Zp+YZ7iV9VVfyBWs/8dzjC/syjg n7Yg=="],"x-google-dkim-signature":["v=1; a=rsa-sha256; c=relaxed/relaxed; d=1e100.net; s=20161025; h=x-gm-message-state:to:auto-submitted:message-id:date:from:subject :references:in-reply-to; bh=XQn9OkLmErA/tAilD7UbDGhZArjQ5DDbS8Ki23X/v58=; b=KBpYfYAvZxfhMkL8fm5z3LQNovY+8LSMDtLWTUR5rYVM9PGVRQb0ydNPiA6IoUnMOP Al+E+8jSEEFzh5vWCQR/K76k8NG36j/xiTzczf5KcxIHAx+c4ujvBxuBUe0jJuOnTyVg U0SCyh8yVGkNkqpvQoVPabZarYLeS+FBmMTpGKqmUB3gykkeRVV44+bMd1Y8/Gqbk7ZF 8cgtQKH2wVpizNvoHgemV1HuU6hgz0YDD/s4q/znaLApShEcydWhW5rkwoHm9cxTwQC8 a2B1rMyzeTpvSOrY9z11NULnGtJ4/X7tTorT5oX0yPtGoYSk11/p2i43/H3AuD5f5W7g JTrg=="],"x-gm-message-state":["APjAAAXfRBlXRvKiSqtVIlvb2qfvVtFZOE0Q/aIBy4rZqRix7XCsofDH I/ProhnRZbyFbJyZkCiNrgUU/eEXnjFplhRI+zIYmA=="],"x-google-smtp-source":["APXvYqwMwKw29aluIlMbWccm1+/XBLBDirNeC6F88EskQ40T0WNL1H+Jmh3nLdYAueshsv3MYXHTAcWWjkWxxmMjEJyezw9TSuWveKY="],"content-type":["multipart/report; boundary=\"000000000000bc324d059de68feb\"; report-type=delivery-status"],"to":["ifchasethenhire@gmail.com"],"auto-submitted":["auto-replied"],"message-id":["<5e3bf82f.1c69fb81.ddb17.b7b8.GMR@mx.google.com>"],"date":["Thu, 06 Feb 2020 03:27:43 -0800 (PST)"],"from":["Mail Delivery Subsystem <mailer-daemon@googlemail.com>"],"subject":["Delivery Status Notification (Failure)"],"references":["<f36c6cda-6920-f111-3afd-25fd4d59d313@gmail.com>"],"in-reply-to":["<f36c6cda-6920-f111-3afd-25fd4d59d313@gmail.com>"],"x-failed-recipients":["Enterprise@trm.brassring.com"]}][{"delivered-to":["ifchasethenhire@gmail.com"],"received":["by 2002:a05:6214:36c:0:0:0:0 with SMTP id t12csp799731qvu; Thu, 6 Feb 2020 10:34:17 -0800 (PST)","from mail78.indeed.com (mail78.indeed.com. [198.58.75.78]) by mx.google.com with ESMTPS id p1si271945otk.42.2020.02.06.10.34.16 for <ifchasethenhire@gmail.com> (version=TLS1_2 cipher=ECDHE-RSA-AES128-GCM-SHA256 bits=128/128); Thu, 06 Feb 2020 10:34:17 -0800 (PST)","from aus-mexec90.indeed.net (aus-smtp3.indeed.net [10.1.3.212]) by mail78.indeed.com (Postfix) with ESMTP id 48D6XS3qG5z7SdpR for <ifchasethenhire@gmail.com>; Thu,  6 Feb 2020 12:34:16 -0600 (CST)"],"x-google-smtp-source":["APXvYqw1sLtRuRPo4tmBf+K5E24LMnWhLKmgWM4vUZ2vEUuyThqb5c6zPd8O5w05RIeA86TzYbtb"],"x-received":["by 2002:aca:ec13:: with SMTP id k19mr7643338oih.22.1581014057294; Thu, 06 Feb 2020 10:34:17 -0800 (PST)"],"arc-seal":["i=1; a=rsa-sha256; t=1581014057; cv=none; d=google.com; s=arc-20160816; b=JUX2iZN/00t4v3ezHIAawRVbghzWM4nAfuJqGU7Ipz80Zu+EOHmxhWdREYbgjfEeh5 IUjfKa/9WYwHs4PT6DA7rfWEpP4PNSNYU1vuLxUny2MiCOBz709RcU96PUUGd/mHiOyK OKZIBxzJnKoa/Snt7bLW6B9ENBrzDWTOu3Ovq40AXry+fqhPd37uyMaKBMKl9v5/f856 Tosuc2Mk6jwRwIMECC4hH5yCT5VQ1W0GEvmWMsPvOec4N12c9+nS/66jKAWQY+/hc4xk xviQS6bAKYKal0ondU4XDkXtG/e72fCGr6toGwp41mK4aUH65bPs+0CsbU0dpCx3BACL Z/iA=="],"arc-message-signature":["i=1; a=rsa-sha256; c=relaxed/relaxed; d=google.com; s=arc-20160816; h=date:feedback-id:list-unsubscribe:preheader:mime-version:subject :message-id:to:reply-to:from:dkim-signature; bh=vSx4J6+cDwyf1srz8YoW4N/Gd8tzcOJ5RKDUMumJDVU=; b=kJ0eSr/DC9Y5MHWEtF0rCdqJw1MBR/Ot6Pu/UEDxhKRqtjoHGDRq/njrSAAXKjGQVR pv5InAjIeiGkeHZWvygYkFJZqRMDwVzK4D9cx1ruHcd7r9aUFEB1iOJ9ejK7BnBr6FMl PrJ5b9s+T8RVrnG/I6VG1Sjbn2MNUZ2IAvJWKM3dHeZiKsNLad8mVtDNe9r4jyt2lKh9 puhljKKVLdsb1xMBlch6sTlOSDXRsltugP9l0WskhwoyJttbj1bpGa1OGt4/K/5mUJbl K7alFxuJlhRhR4dgM1RJ0ZN4fIDaFhN3eJNxAopNZiqvU3Jnfdm04K8p2ZQqDOz+qS3F SNrA=="],"arc-authentication-results":["i=1; mx.google.com; dkim=pass header.i=@indeed.com header.s=default header.b=q0jZPiI2; spf=pass (google.com: domain of alert@indeed.com designates 198.58.75.78 as permitted sender) smtp.mailfrom=alert@indeed.com; dmarc=pass (p=QUARANTINE sp=QUARANTINE dis=NONE) header.from=indeed.com"],"return-path":["<alert@indeed.com>"],"received-spf":["pass (google.com: domain of alert@indeed.com designates 198.58.75.78 as permitted sender) client-ip=198.58.75.78;"],"authentication-results":["mx.google.com; dkim=pass header.i=@indeed.com header.s=default header.b=q0jZPiI2; spf=pass (google.com: domain of alert@indeed.com designates 198.58.75.78 as permitted sender) smtp.mailfrom=alert@indeed.com; dmarc=pass (p=QUARANTINE sp=QUARANTINE dis=NONE) header.from=indeed.com"],"dkim-signature":["v=1; a=rsa-sha256; c=relaxed/simple; d=indeed.com; s=default; t=1581014056; bh=vSx4J6+cDwyf1srz8YoW4N/Gd8tzcOJ5RKDUMumJDVU=; h=From:Reply-To:To:Subject:List-Unsubscribe:Date; b=q0jZPiI2aLRYihktrPeDqPENeV0ugmRjG69x4Cd6GVSSarXqU1WYFTgHV5ice+SwT 7BSZhS3yDA/w9MPwpMwCMpoufycI86j7VhOvJ1zra6nTa9KQh8UMeG2cBDJ4PnVtp3 DK9FD6q6xpOTuvDOxXaFlmH73lTu1UU+LjfXNJnM="],"from":["Indeed <alert@indeed.com>"],"reply-to":["Indeed <do-not-reply@indeed.com>"],"to":["ifchasethenhire@gmail.com"],"message-id":["<1e0dsfoglo33t800.1581014056511.Railgunner@aus-mexec18.indeed.net>"],"subject":["Interface Human, Inc. is hiring for Sr. and Jr. Full-stack .NET Developers. 18 more node.js remote jobs."],"mime-version":["1.0"],"content-type":["multipart/alternative; boundary=\"----=_Part_179941386_191760070.1581014056534\""],"preheader":["Apply now at Red Ventures, Globant, and Dolphin"],"list-unsubscribe":["<mailto:arf-feedback@indeed.com?subject=mailtoTag:5e39b340e75c9e6bc0031063:JOBALERT:RailgunnerDaemon:1e0dsfvi02gdq800:1e0dsfoglo33t800:indeed.com:2>"],"feedback-id":["JOBALERT:RailgunnerDaemon:Indeed"],"x-indeed-fbl":["5e39b340e75c9e6bc0031063:2:e901e11e78b40456485d1f3ddd03b030217d355ac31a5ae7bcd96619c43d6f4f"],"x-indeed-client-app":["RailgunnerDaemon"],"x-indeed-content-type":["JOBALERT"],"x-indeed-tk":["1e0dsfvi02gdq800"],"date":["Thu,  6 Feb 2020 12:34:16 -0600 (CST)"]}][{"delivered-to":["ifchasethenhire@gmail.com"],"received":["by 2002:a05:6214:36c:0:0:0:0 with SMTP id t12csp833126qvu; Thu, 6 Feb 2020 11:10:54 -0800 (PST)","from o1678934x219.outbound-mail.sendgrid.net (o1678934x219.outbound-mail.sendgrid.net. [167.89.34.219]) by mx.google.com with ESMTPS id u1si138083edl.395.2020.02.06.11.10.53 for <ifchasethenhire@gmail.com> (version=TLS1_2 cipher=ECDHE-RSA-AES128-GCM-SHA256 bits=128/128); Thu, 06 Feb 2020 11:10:54 -0800 (PST)","by filter1823p1mdw1.sendgrid.net with SMTP id filter1823p1mdw1-1203-5E3C64B8-27 2020-02-06 19:10:48.641170785 +0000 UTC m=+177194.973652714","from zipalerts.com (ec2-52-23-117-207.compute-1.amazonaws.com [52.23.117.207]) by ismtpd0036p1iad2.sendgrid.net (SG) with ESMTP id X33JqmXyTpK1187VH1mgXg for <ifchasethenhire@gmail.com>; Thu, 06 Feb 2020 19:10:48.664 +0000 (UTC)"],"x-google-smtp-source":["APXvYqz+sNrJ4AsZD+4QhhB/JNjniNxS4FiDQBvUTS043JN2WK58WqUItbAnyT/nk4KUtigbrS5M"],"x-received":["by 2002:a17:906:bb04:: with SMTP id jz4mr4697342ejb.183.1581016254510; Thu, 06 Feb 2020 11:10:54 -0800 (PST)"],"arc-seal":["i=1; a=rsa-sha256; t=1581016254; cv=none; d=google.com; s=arc-20160816; b=NPSrBY2I//G2Pd00+g8HDyXraQiaw25qpBxx7CEEvtJV1bC9j+9plCGKlAlwUU11gd CL8mHs5GF5MsHzabX0se/Ydr5+DScRiidfnZ3DxDb8SnuvSiTYgyGRv1f6+az4ZH72Xe MvZb7psibzM0MXoT6IFvmxUhxH/0WiJ/dyKNkhLcJYSmxL1hA0S2vLR//BrVx6i3382g 4O7P/joZmaiLaGJyrvg7aEwVrTdnjfGIZXi6u7u+g/Cx5aFRkH7n+kHMeQ9cKjlkW3x6 2LVKOUrzWmPx9Rb/qUrAPmceJ6Q3LCdq6nEzsgdQwNraI6EZrA4FukPzyCnOJMPPdvdZ 61/g=="],"arc-message-signature":["i=1; a=rsa-sha256; c=relaxed/relaxed; d=google.com; s=arc-20160816; h=message-id:reply-to:from:to:subject:content-disposition :content-transfer-encoding:mime-version:date:dkim-signature :dkim-signature; bh=GYFx57EltOpaG4w5bT3PWgZssn/cemqC6jouRbmQctI=; b=T4HZIzzTnIJVGHQ62cQjdtrzbqzM/fdrloYqq2VmrHK1gthRQmeAdUMrEhv18mm045 OokljfQkWuayP4paAuVoO/1THW8J0gUMSABB3OCMEnn3QSidQy0ZbhlLG89PGICZt80R 0PWjgCNBcHT+6hNwQxaQ7NF0nV5Cj3zY/HFE0wvgDZrYv9YVuoEZw1QjOKheLqg+8IdV yKvYOhsN7qh6Pb5Kiw2rrw+fVTxo0J1wr+oIwVTw2e8IhIQE5YIm8zXdpey/PbDDp9dq iUfnM3RSSI9zGOPSBnRQMsPkznTBi7GCrrOaYCw8Wj4ZSRA0KasicQTv/odEv4D0FzbV ZJ2w=="],"arc-authentication-results":["i=1; mx.google.com; dkim=pass header.i=@sendgrid.ziprecruiter.com header.s=smtpapi header.b=Cx37mqG2; dkim=pass header.i=@sendgrid.info header.s=smtpapi header.b=FmuhPGka; spf=pass (google.com: domain of bounces+1349816-0068-ifchasethenhire=gmail.com@sendgrid.ziprecruiter.com designates 167.89.34.219 as permitted sender) smtp.mailfrom=\"bounces+1349816-0068-ifchasethenhire=gmail.com@sendgrid.ziprecruiter.com\"; dmarc=pass (p=QUARANTINE sp=NONE dis=NONE) header.from=ziprecruiter.com"],"return-path":["<bounces+1349816-0068-ifchasethenhire=gmail.com@sendgrid.ziprecruiter.com>"],"received-spf":["pass (google.com: domain of bounces+1349816-0068-ifchasethenhire=gmail.com@sendgrid.ziprecruiter.com designates 167.89.34.219 as permitted sender) client-ip=167.89.34.219;"],"authentication-results":["mx.google.com; dkim=pass header.i=@sendgrid.ziprecruiter.com header.s=smtpapi header.b=Cx37mqG2; dkim=pass header.i=@sendgrid.info header.s=smtpapi header.b=FmuhPGka; spf=pass (google.com: domain of bounces+1349816-0068-ifchasethenhire=gmail.com@sendgrid.ziprecruiter.com designates 167.89.34.219 as permitted sender) smtp.mailfrom=\"bounces+1349816-0068-ifchasethenhire=gmail.com@sendgrid.ziprecruiter.com\"; dmarc=pass (p=QUARANTINE sp=NONE dis=NONE) header.from=ziprecruiter.com"],"dkim-signature":["v=1; a=rsa-sha256; c=relaxed/relaxed; d=sendgrid.ziprecruiter.com; h=mime-version:content-type:content-transfer-encoding:subject:to:from:reply-to; s=smtpapi; bh=GYFx57EltOpaG4w5bT3PWgZssn/cemqC6jouRbmQctI=; b=Cx 37mqG2320VniczfLsOvWk724HgmrY7s1HZMjTLDvZmFHcqKfiKtHVNLFKjgoF8ho MKjsSIkvrDTesao/6EYl5HrhCBd68V66Xf1+b1rDQL5SNpKmc0IQloz0ooy/RGTh d5DHYctqPJzljJo9r5YO4GEACGg+fIVjsWbeNObGs=","v=1; a=rsa-sha256; c=relaxed/relaxed; d=sendgrid.info; h=mime-version:content-type:content-transfer-encoding:subject:to:from:reply-to:x-feedback-id; s=smtpapi; bh=GYFx57EltOpaG4w5bT3PWgZssn/cemqC6jouRbmQctI=; b=Fm uhPGka9S/7+k1KbfBcOdYP+jCamOU0qbrAzQCemlicytSizg8yjK9+t9PwFR/DFF wuRy7UMzlZ3Bs+69M4C+ODzhLy1nhL1YGg48jpaNA/2Fhb1mJAddws6rcpdZygF8 z9Jk53TiisRKjAwUxVrCYSlEGxOTAkEnGfKosSCcY="],"date":["Thu, 06 Feb 2020 19:10:48 +0000 (UTC)"],"mime-version":["1.0"],"content-type":["text/html; charset=\"UTF-8\""],"content-transfer-encoding":["quoted-printable"],"content-disposition":["inline"],"subject":["Your Application for Full Stack JavaScript Engineer"],"to":["ifchasethenhire@gmail.com"],"from":["\"Amanda C. from Information Technology Professionals LLC\" <hiring_manager_messages@ziprecruiter.com>"],"reply-to":["c_217b7a7b.4e2a24c0.35b0f89c-ced5-432a-a651-306340455f4a.f87c0e3a4faad31dcdb6b2812f017595@messages.ziprecruiter.com"],"message-id":["<X33JqmXyTpK1187VH1mgXg@ismtpd0036p1iad2.sendgrid.net>"],"x-sg-eid":["1lu6SIF4WSwa0DaFwyLhTcTp+f5SGVRqGv0oM04PbxWO5ttHeC6JQNCtpgTNtVl3GCqQRQjDm03uFL Yo87lDuEMosh/20+osa78oLsR7SAm2NDd9eMyzLc37beg501yFXnU72GRDnmhh6vkL7EKbp+Fsnw9p 80BX0yXsKadVLCGbdmxJ4SOv6xjdcl+S/4O3yd0Yy/Uc21nhEfDhNZ9nRPZoMaUGMYKrxg0Wd0qQB7 C9YCnSS7UO7yA99QQiJdnVy1NQKFPlgibK+8W0qnu8OvKu+xog9g1Etk31raEt5pGZtKIcZoq046Ib Hj2cystw"],"x-sg-id":["trnf54TTjAb91d6Ywfb3bh3BmeQCHiosUaVWK/fxndCXFMRQ7N9P5zj9ALKMP1eHzDNh3iCp17IaKQ tiXkr2G5TX8yFNClaju0PM6yGPNtikUWbUkySbYygpJHd+t2cGPetGQs6kk9QtLjHTH1EW4v/h5B0a eqcwEiV1FHsTdU8JdNv4Vu/mUijqIpCpsvuht9S+5T1ftjfNdXfR9Am2FSlStoMku9B2ZlhUVBa5Lj 0L8vZ4vu8c2Ojouia91f3LEtx1/mNyZJ1rfjpIwTN6xA=="],"x-feedback-id":["1349816:eGDQMyIZaWn90IfJZhueBWY695q58j5mCmtjWrOdLLk=:eIYLPfWSgHHxNsK1bOWJH9ZtznKq82XQmluMd9MpWJDdyQw13GiHQinHlSBG3G+g:SG"]}][{"delivered-to":["ifchasethenhire@gmail.com"],"received":["by 2002:a05:6214:36c:0:0:0:0 with SMTP id t12csp833522qvu; Thu, 6 Feb 2020 11:11:17 -0800 (PST)","from mail-sor-f69.google.com (mail-sor-f69.google.com. [209.85.220.69]) by mx.google.com with SMTPS id 75sor383820pfb.53.2020.02.06.11.11.17 for <ifchasethenhire@gmail.com> (Google Transport Security); Thu, 06 Feb 2020 11:11:17 -0800 (PST)"],"x-received":["by 2002:a17:90a:3188:: with SMTP id j8mr6159153pjb.82.1581016277095; Thu, 06 Feb 2020 11:11:17 -0800 (PST)","by 2002:aa7:9a01:: with SMTP id w1mr5315662pfj.231.1581016276755; Thu, 06 Feb 2020 11:11:16 -0800 (PST)"],"arc-seal":["i=1; a=rsa-sha256; t=1581016277; cv=none; d=google.com; s=arc-20160816; b=0SVqQ7U3HoTEfeySD5/N9vgK3UIsw+N3wkbEtmoCcqzQmN9aJ64oP1XL4VB8jgpTJL ZKPH8tjmF4M72DKMDcN1ZvBACyRaSgR1R3yw6w9Sr/mUe1/BJuEZwXa3DkUzjIaUUU+j GvGCEnZxNi7Wyju/kEYf8HHmPHvp5eZNptSrnCORiVPENQkKJ2nJ0zBaZ341o8WPasG1 f98k6jcFqvxaCYcv3fdrzQqknfAXLA+KgqJ0yrpVwJwMXdsW+QUhlybbneY4hGQfafMQ RIqnHxWVDEyfcS5i9c+o6C3Cc4kdOJ0ED4Nos/ncfJa1TAYvHpDU65oonBGfaS4Sry9M RMag=="],"arc-message-signature":["i=1; a=rsa-sha256; c=relaxed/relaxed; d=google.com; s=arc-20160816; h=date:message-id:subject:to:from:references:in-reply-to :auto-submitted:mime-version:dkim-signature; bh=9QTJKHoZgoeztOZY4YcIsd2UmlB/oZodIgrjwkTKmHg=; b=hjSAy559JJ7Q6MVLA2fs2s5R9qPlaCaSXdWJn+6bhq8BxAmWQp3lMyDV0I/tY1dpwW bDtier9XhES96iG7UtwsmQYS+/KDTGtyHqB2dIyW75neul5DCgKQnJUiOytdExbE667H TqZjEzlMSfiS3Ft5MwvGqvGfFLYOdJoPyFshK/8zIcxk12OIIQND1ka6KpVP2sPNxbCR 4Gvu19OzSzdcrBcWRSx0WoRxNA3BabfCe5YXZOOjurPbElfLIz18+VM0unyx/uJUNSQG 7BCAayaCdcWfbD2Tyuuc1ogVkracrRBBNI4KPBPkCGsFpKKIkmV8NbBM6pvHaCu5bjwG plhA=="],"arc-authentication-results":["i=1; mx.google.com; dkim=pass header.i=@ziprecruiter.com header.s=google header.b=aHmC3DZj; spf=pass (google.com: domain of 31gq8xh8qaicst2tyr_xlylrp2_xp33lrp3+yz2p0w9at02pn25t4p2.nzx@listserv.bounces.google.com designates 209.85.220.69 as permitted sender) smtp.mailfrom=31GQ8Xh8QAIcst2tyr_xlylrp2_xp33lrp3+yz2p0w9At02pn25t4p2.nzx@listserv.bounces.google.com; dmarc=pass (p=QUARANTINE sp=NONE dis=NONE) header.from=ziprecruiter.com"],"return-path":["<31GQ8Xh8QAIcst2tyr_xlylrp2_xp33lrp3+yz2p0w9At02pn25t4p2.nzx@listserv.bounces.google.com>"],"received-spf":["pass (google.com: domain of 31gq8xh8qaicst2tyr_xlylrp2_xp33lrp3+yz2p0w9at02pn25t4p2.nzx@listserv.bounces.google.com designates 209.85.220.69 as permitted sender) client-ip=209.85.220.69;"],"authentication-results":["mx.google.com; dkim=pass header.i=@ziprecruiter.com header.s=google header.b=aHmC3DZj; spf=pass (google.com: domain of 31gq8xh8qaicst2tyr_xlylrp2_xp33lrp3+yz2p0w9at02pn25t4p2.nzx@listserv.bounces.google.com designates 209.85.220.69 as permitted sender) smtp.mailfrom=31GQ8Xh8QAIcst2tyr_xlylrp2_xp33lrp3+yz2p0w9At02pn25t4p2.nzx@listserv.bounces.google.com; dmarc=pass (p=QUARANTINE sp=NONE dis=NONE) header.from=ziprecruiter.com"],"dkim-signature":["v=1; a=rsa-sha256; c=relaxed/relaxed; d=ziprecruiter.com; s=google; h=mime-version:auto-submitted:in-reply-to:references:from:to:subject :message-id:date; bh=9QTJKHoZgoeztOZY4YcIsd2UmlB/oZodIgrjwkTKmHg=; b=aHmC3DZjJuGwYaNtndJ/PxphFbW15On7gB9jrnDmuBzTpDibsa+8jFETfnHZ96UI6Y I21vX09wvjsC3BnRSnjq+K+dP7MOq5f7EJD2kxLizxUsdS4YyczT4hYbZfxf2SRKrlkL lUEUgP4Hb2HQ4bIlytrX5sfZAxq3m2DQXxVRE="],"x-google-dkim-signature":["v=1; a=rsa-sha256; c=relaxed/relaxed; d=1e100.net; s=20161025; h=x-gm-message-state:mime-version:auto-submitted:in-reply-to :references:from:to:subject:message-id:date; bh=9QTJKHoZgoeztOZY4YcIsd2UmlB/oZodIgrjwkTKmHg=; b=FMCenj6msiDG92bRmLKdy4o4EITXTSQnJjcKKCE76JanOKFySMIrFf5cjlSTtVTXCi F1/ZwT6ZeLfJnQ3pGXrLH6rsT4aCN7tTtX53Bsoa44lce/fyClLUIMat4DcJZ+L1luSe vaaAk2f5S6B+cSsVsluAUDf4kg/XKzw5SCZ+H1ddNIJCAMD4wB/LNFfp8QXzdNx9oeEE zR5aYdSFX3eB/0YwL5q3QO5SjljhUWY1omzITfN/cYFtG0tRoYRIdEDoBeq4vvVIAwyf 56FnSp8sITkuU1+zQX6jRTotwvL0qD42Eqnl6PyIivtQ3EuJhR1TeZBDO7LL9CKLfNUJ 73oA=="],"x-gm-message-state":["APjAAAUwfxtpMBufDrYL7C2lw6bRdZrT8MOz2cNdjJEYXAKyLoYcz86u tug7PI234TaDllzdTp9zpxVFZpo/EZYYPTWF5Iru7r7StDo="],"x-google-smtp-source":["APXvYqzcL6mTYcpAv1ASgr0x653Sqgm+6ZMgiZyLc4PBixPJM0RSxAMBlzz33VWusiuCFY+CHMcDMfL/3S0fPyO3/Y75xfLG"],"mime-version":["1.0"],"auto-submitted":["auto-replied"],"in-reply-to":["<092b4c2a-fc42-c7ef-3014-8500b13461e2@gmail.com>"],"references":["<092b4c2a-fc42-c7ef-3014-8500b13461e2@gmail.com>"],"from":["Hiring Manager Messages <hiring_manager_messages+noreply@ziprecruiter.com>"],"to":["<ifchasethenhire@gmail.com>"],"subject":["Re: Hey beautiful!"],"message-id":["<0000000000008f6274059ded09a2@google.com>"],"date":["Thu, 06 Feb 2020 19:11:16 +0000"],"content-type":["text/plain; charset=\"UTF-8\""]}]